{"v":"5.5.10","fr":25,"ip":0,"op":50,"w":156,"h":250,"nm":"lock and unlock","ddd":0,"assets":[],"layers":[{"ddd":0,"ind":1,"ty":4,"nm":"lock and unlock contornos","sr":1,"ks":{"o":{"a":0,"k":100,"ix":11},"r":{"a":0,"k":0,"ix":10},"p":{"a":0,"k":[78.00000000000003,125.00000000000004,0],"ix":2},"a":{"a":0,"k":[78,125,0],"ix":1},"s":{"a":0,"k":[100,100.00000000000003,100],"ix":6}},"ao":0,"shapes":[{"ty":"gr","it":[{"ty":"gr","it":[{"ind":0,"ty":"sh","ix":1,"ks":{"a":0,"k":{"i":[[0,0],[3.767,0],[0,-3.767],[0,0],[-3.767,0],[0,3.767]],"o":[[0,-3.767],[-3.767,0],[0,0],[0,3.767],[3.767,0],[0,0]],"v":[[6.826,-14.69],[0.001,-21.514],[-6.826,-14.69],[-6.826,14.689],[0.001,21.514],[6.826,14.689]],"c":true},"ix":2},"nm":"Caminho 1","mn":"ADBE Vector Shape - Group","hd":false},{"ty":"fl","c":{"a":0,"k":[1,1,1,1],"ix":4},"o":{"a":0,"k":100,"ix":5},"r":1,"bm":0,"nm":"Preenchimento 1","mn":"ADBE Vector Graphic - Fill","hd":false},{"ty":"tr","p":{"a":0,"k":[78.467,187.572],"ix":2},"a":{"a":0,"k":[0,0],"ix":1},"s":{"a":0,"k":[100,100],"ix":3},"r":{"a":0,"k":0,"ix":6},"o":{"a":0,"k":100,"ix":7},"sk":{"a":0,"k":0,"ix":4},"sa":{"a":0,"k":0,"ix":5},"nm":"Transformar"}],"nm":"Grupo 1","np":2,"cix":2,"bm":0,"ix":1,"mn":"ADBE Vector Group","hd":false},{"ty":"gr","it":[{"ind":0,"ty":"sh","ix":1,"ks":{"a":0,"k":{"i":[[-9.193,0],[0,-9.194],[9.194,0],[0,9.194]],"o":[[9.194,0],[0,9.194],[-9.193,0],[0,-9.194]],"v":[[0,-16.658],[16.658,0.001],[0,16.658],[-16.658,0.001]],"c":true},"ix":2},"nm":"Caminho 1","mn":"ADBE Vector Shape - Group","hd":false},{"ty":"fl","c":{"a":0,"k":[1,1,1,1],"ix":4},"o":{"a":0,"k":100,"ix":5},"r":1,"bm":0,"nm":"Preenchimento 1","mn":"ADBE Vector Graphic - Fill","hd":false},{"ty":"tr","p":{"a":0,"k":[77.934,170.15],"ix":2},"a":{"a":0,"k":[0,0],"ix":1},"s":{"a":0,"k":[100,100],"ix":3},"r":{"a":0,"k":0,"ix":6},"o":{"a":0,"k":100,"ix":7},"sk":{"a":0,"k":0,"ix":4},"sa":{"a":0,"k":0,"ix":5},"nm":"Transformar"}],"nm":"Grupo 2","np":2,"cix":2,"bm":0,"ix":2,"mn":"ADBE Vector Group","hd":false},{"ty":"tr","p":{"a":1,"k":[{"i":{"x":0.833,"y":0.833},"o":{"x":0.167,"y":0.167},"t":0,"s":[77.934,181.289],"to":[0,-6.667],"ti":[0,0]},{"i":{"x":0.833,"y":0.833},"o":{"x":0.167,"y":0.167},"t":6,"s":[77.934,141.289],"to":[0,0],"ti":[0,-6.667]},{"i":{"x":0.833,"y":0.833},"o":{"x":0.167,"y":0.167},"t":12,"s":[77.934,181.289],"to":[0,0],"ti":[0,0]},{"i":{"x":0.833,"y":0.833},"o":{"x":0.167,"y":0.167},"t":24,"s":[77.934,181.289],"to":[0,-6.667],"ti":[0,0]},{"i":{"x":0.833,"y":0.833},"o":{"x":0.167,"y":0.167},"t":30,"s":[77.934,141.289],"to":[0,0],"ti":[0,-6.667]},{"t":36,"s":[77.934,181.289]}],"ix":2},"a":{"a":0,"k":[77.934,181.289],"ix":1},"s":{"a":0,"k":[100,100],"ix":3},"r":{"a":0,"k":0,"ix":6},"o":{"a":0,"k":100,"ix":7},"sk":{"a":0,"k":0,"ix":4},"sa":{"a":0,"k":0,"ix":5},"nm":"Transformar"}],"nm":"Grupo 5","np":2,"cix":2,"bm":0,"ix":1,"mn":"ADBE Vector Group","hd":false},{"ty":"gr","it":[{"ind":0,"ty":"sh","ix":1,"ks":{"a":1,"k":[{"i":{"x":0.833,"y":0.833},"o":{"x":0.167,"y":0.167},"t":0,"s":[{"i":[[0,0],[-0.019,3.727],[0.622,-55.29],[0.027,-4.595]],"o":[[-0.04,-3.804],[1.246,-61.328],[-0.017,1.524],[0,0]],"v":[[-39.902,59.398],[-39.891,1.93],[39.319,1.212],[39.172,18.263]],"c":false}]},{"i":{"x":0.833,"y":0.833},"o":{"x":0.167,"y":0.167},"t":6,"s":[{"i":[[0,0],[-0.019,3.727],[0.622,-55.29],[0.027,-4.595]],"o":[[-0.04,-3.804],[1.246,-61.328],[-0.017,1.524],[0,0]],"v":[[-39.902,59.398],[-39.891,1.93],[39.319,1.212],[39.172,18.263]],"c":false}]},{"i":{"x":0.833,"y":0.833},"o":{"x":0.167,"y":0.167},"t":8,"s":[{"i":[[0,0],[-0.019,3.727],[0.617,-55.29],[0.027,-4.595]],"o":[[-0.04,-3.804],[1.246,-61.328],[-0.017,1.524],[0,0]],"v":[[-40.402,61.398],[-41.141,26.555],[38.069,25.837],[38.047,61.263]],"c":false}]},{"i":{"x":0.833,"y":0.833},"o":{"x":0.167,"y":0.167},"t":30,"s":[{"i":[[0,0],[-0.019,3.727],[0.617,-55.29],[0.027,-4.595]],"o":[[-0.04,-3.804],[1.246,-61.328],[-0.017,1.524],[0,0]],"v":[[-40.402,61.398],[-41.141,26.555],[38.069,25.837],[38.047,61.263]],"c":false}]},{"t":32,"s":[{"i":[[0,0],[-0.019,3.727],[0.622,-55.29],[0.027,-4.595]],"o":[[-0.04,-3.804],[1.246,-61.328],[-0.017,1.524],[0,0]],"v":[[-39.902,59.398],[-39.891,1.93],[39.319,1.212],[39.172,18.263]],"c":false}]}],"ix":2},"nm":"Caminho 1","mn":"ADBE Vector Shape - Group","hd":false},{"ty":"st","c":{"a":0,"k":[1,1,1,1],"ix":3},"o":{"a":0,"k":100,"ix":4},"w":{"a":0,"k":9,"ix":5},"lc":2,"lj":2,"bm":0,"nm":"Traçado 1","mn":"ADBE Vector Graphic - Stroke","hd":false},{"ty":"tr","p":{"a":1,"k":[{"i":{"x":0.833,"y":0.833},"o":{"x":0.167,"y":0.167},"t":0,"s":[81.432,47.539],"to":[0,-0.25],"ti":[0,0.25]},{"t":8,"s":[81.432,46.039]}],"ix":2},"a":{"a":0,"k":[0,0],"ix":1},"s":{"a":0,"k":[100,100],"ix":3},"r":{"a":0,"k":0,"ix":6},"o":{"a":0,"k":100,"ix":7},"sk":{"a":0,"k":0,"ix":4},"sa":{"a":0,"k":0,"ix":5},"nm":"Transformar"}],"nm":"Grupo 3","np":2,"cix":2,"bm":0,"ix":2,"mn":"ADBE Vector Group","hd":false},{"ty":"gr","it":[{"ind":0,"ty":"sh","ix":1,"ks":{"a":0,"k":{"i":[[0,0],[0,0],[0,0],[0,0],[0,0],[0,0],[0,0],[0,0],[0,0],[0,0],[0,0],[0,0],[0,0],[0,0],[0,0],[0,0],[0,0],[0,0],[0,0],[0,0],[0,0],[0,0],[0,0],[0,0],[0,0],[0,0],[0,0],[0,0],[0,0],[0,0],[0,0],[0,0],[0,0],[0,0],[0,0],[0,0],[0,0],[0,0],[0,0],[0,0],[0,0],[0,0],[0,0],[0,0],[0,0],[0,0],[0,0],[0,0],[0,0],[0,0],[0,0],[0,0],[0,0],[0,0],[0,0],[0,0],[0,0],[0,0],[0,0],[0,0],[0,0],[0,0],[0,0],[0,0],[0,0],[0,0],[0,0],[0,0],[0,0],[0,0],[0,0],[0,0],[0,0],[0,0],[0,0],[0,0],[0,0],[0,0],[0,0],[0,0],[0,0],[0,0],[0,0],[0,0],[0,0],[0,0],[0,0],[0,0],[0,0],[0,0],[0,0],[0,0],[0,0],[0,0],[0,0],[0,0],[0,0],[0,0],[0,0],[0,0],[0,0],[0,0],[0,0],[0,0],[0,0],[0,0],[0,0],[0,0],[0,0],[0,0],[0,0],[0,0],[0,0],[0,0],[0,0],[0,0],[0,0],[0,0],[0,0],[0,0],[0,0],[0,0],[0,0],[0,0],[0,0],[0,0],[0,0],[0,0],[0,0],[0,0],[0,0],[0,0],[0,0],[0,0],[0,0],[0,0],[0,0],[0,0],[0,0],[0,0],[0,0],[0,0],[0,0],[0,0],[0,0],[0,0],[0,0],[0,0],[0,0],[0,0],[0,0],[0,0],[0,0],[0,0],[0,0],[0,0],[0,0],[0,0],[0,0],[0,0],[0,0],[0,0],[0,0],[0,0],[0,0],[0,0],[0,0],[0,0],[0,0],[0,0],[0,0],[0,0],[0,0],[0,0],[0,0],[0,0],[0,0],[0,0],[0,0],[0,0],[0,0],[0,0],[0,0],[0,0],[0,0],[0,0],[0,0],[0,0],[0,0],[0,0],[0,0],[0,0],[0,0],[0,0],[0,0],[0,0],[0,0],[0,0],[0,0],[0,0],[0,0],[0,0],[0,0],[0,0],[0,0],[0,0],[0,0],[0,0],[0,0],[0,0],[0,0],[0,0],[0,0],[0,0],[0,0],[0,0],[0,0],[0,0],[0,0],[0,0],[0,0],[0,0],[0,0],[0,0],[0,0],[0,0],[0,0],[0,0],[0,0],[0,0],[0,0],[0,0],[0,0],[0,0],[0,0],[0,0],[0,0],[0,0],[0,0],[0,0],[0,0],[0,0],[0,0],[0,0],[0,0],[0,0],[0,0],[0,0],[0,0],[0,0],[0,0],[0,0],[0,0],[0,0],[0,0],[0,0],[0,0],[0,0],[0,0],[0,0],[0,0],[0,0],[0,0],[0,0],[0,0],[0,0],[0,0],[0,0],[0,0],[0,0],[0,0],[0,0],[0,0],[0,0],[0,0],[0,0],[0,0],[0,0],[0,0],[0,0],[0,0],[0,0],[0,0],[0,0],[0,0],[0,0],[0,0],[0,0],[0,0],[0,0],[0,0],[0,0],[0,0],[0,0],[0,0],[0,0],[0,0],[0,0],[0,0],[0,0],[0,0],[0,0],[0,0],[0,0],[0,0],[0,0],[0,0],[0,0],[0,0],[0,0],[0,0],[0,0],[0,0],[0,0],[0,0],[0,0],[0,0],[0,0],[0,0],[0,0],[0,0],[0,0],[0,0],[0,0],[0,0],[0,0],[0,0],[0,0],[0,0],[0,0],[0,0],[0,0],[0,0],[0,0],[0,0],[0,0],[0,0],[0,0],[0,0],[0,0],[0,0],[0,0],[0,0],[0,0],[0,0],[0,0],[0,0],[0,0],[0,0],[0,0],[0,0],[0,0],[0,0],[0,0],[0,0],[0,0],[0,0],[0,0],[0,0],[0,0],[0,0],[0,0],[0,0],[0,0],[0,0],[0,0],[0,0],[0,0],[0,0],[0,0],[0,0],[0,0],[0,0],[0,0],[0,0],[0,0],[0,0],[0,0],[0,0],[0,0],[0,0],[0,0],[0,0],[0,0],[0,0],[0,0],[0,0],[0,0],[0,0],[0,0],[0,0],[0,0],[0,0],[0,0],[0,0],[0,0],[0,0],[0,0],[0,0],[0,0],[0,0],[0,0],[0,0],[0,0],[0,0],[0,0],[0,0],[0,0],[0,0],[0,0],[0,0],[0,0],[0,0],[0,0],[0,0],[0,0],[0,0],[0,0],[0,0],[0,0],[0,0],[0,0],[0,0],[0,0],[0,0],[0,0],[0,0],[0,0],[0,0],[0,0],[0,0],[0,0],[0,0],[0,0],[0,0],[0,0],[0,0],[0,0],[0,0],[0,0],[0,0],[0,0],[0,0],[0,0],[0,0],[0,0],[0,0],[0,0],[0,0],[0,0],[0,0],[0,0],[0,0],[0,0],[0,0],[0,0],[0,0],[0,0],[0,0],[0,0],[0,0],[0,0],[0,0],[0,0],[0,0],[0,0],[0,0],[0,0],[0,0],[0,0],[0,0],[0,0],[0,0],[0,0],[0,0],[0,0],[0,0],[0,0],[0,0],[0,0],[0,0],[0,0],[0,0],[0,0],[0,0],[0,0],[0,0],[0,0],[0,0],[0,0],[0,0],[0,0],[0,0],[0,0],[0,0],[0,0],[0,0],[0,0],[0,0],[0,0],[0,0],[0,0],[0,0],[0,0],[0,0],[0,0],[0,0],[0,0],[0,0],[0,0],[0,0],[0,0],[0,0],[0,0],[0,0],[0,0],[0,0],[0,0],[0,0],[0,0],[0,0],[0,0],[0,0],[0,0],[0,0],[0,0],[0,0],[0,0],[0,0],[0,0],[0,0],[0,0],[0,0],[0,0],[0,0],[0,0],[0,0],[0,0],[0,0],[0,0],[0,0],[0,0],[0,0],[0,0],[0,0],[0,0],[0,0],[0,0],[0,0],[0,0],[0,0],[0,0],[0,0],[0,0],[0,0],[0,0],[0,0],[0,0],[0,0],[0,0],[0,0],[0,0],[0,0],[0,0],[0,0],[0,0],[0,0],[0,0],[0,0],[0,0],[0,0],[0,0],[0,0],[0,0],[0,0],[0,0],[0,0],[0,0],[0,0],[0,0],[0,0],[0,0],[0,0],[0,0],[0,0],[0,0],[0,0],[0,0],[0,0],[0,0],[0,0],[0,0],[0,0],[0,0],[0,0],[0,0],[0,0],[0,0],[0,0],[0,0],[0,0],[0,0],[0,0],[0,0],[0,0],[0,0],[0,0],[0,0],[0,0],[0,0],[0,0],[0,0],[0,0],[0,0],[0,0],[0,0],[0,0],[0,0],[0,0],[0,0],[0,0],[0,0],[0,0],[0,0],[0,0],[0,0],[0,0],[0,0],[0,0],[0,0],[0,0],[0,0],[0,0],[0,0],[0,0],[0,0],[0,0],[0,0],[0,0],[0,0],[0,0],[0,0],[0,0],[0,0],[0,0],[0,0],[0,0],[0,0],[0,0],[0,0],[0,0],[0,0],[0,0],[0,0],[0,0],[0,0],[0,0],[0,0],[0,0],[0,0],[0,0],[0,0],[0,0],[0,0],[0,0],[0,0],[0,0],[0,0],[0,0],[0,0],[0,0],[0,0],[0,0],[0,0],[0,0],[0,0],[0,0],[0,0],[0,0],[0,0],[0,0],[0,0],[0,0],[0,0],[0,0],[0,0],[0,0],[0,0],[0,0],[0,0],[0,0],[0,0],[0,0],[0,0],[0,0],[0,0],[0,0],[0,0],[0,0],[0,0],[0,0],[0,0],[0,0],[0,0],[0,0],[0,0],[0,0],[0,0],[0,0],[0,0],[0,0],[0,0],[0,0],[0,0],[0,0],[0,0],[0,0],[0,0],[0,0],[0,0],[0,0],[0,0],[0,0],[0,0],[0,0],[0,0],[0,0],[0,0],[0,0],[0,0],[0,0],[0,0],[0,0],[0,0],[0,0],[0,0],[0,0],[0,0],[0,0],[0,0],[0,0],[0,0],[0,0],[0,0],[0,0],[0,0],[0,0],[0,0],[0,0],[0,0],[0,0],[0,0],[0,0],[0,0],[0,0],[0,0],[0,0],[0,0],[0,0],[0,0],[0,0],[0,0],[0,0],[0,0],[0,0],[0,0],[0,0],[0,0],[0,0],[0,0],[0,0],[0,0],[0,0],[0,0],[0,0],[0,0],[0,0],[0,0],[0,0],[0,0],[0,0],[0,0],[0,0],[0,0],[0,0],[0,0],[0,0],[0,0],[0,0],[0,0],[0,0],[0,0],[0,0],[0,0],[0,0],[0,0],[0,0],[0,0],[0,0],[0,0],[0,0],[0,0],[0,0],[0,0],[0,0],[0,0],[0,0],[0,0],[0,0],[0,0],[0,0],[0,0],[0,0],[0,0],[0,0],[0,0],[0,0],[0,0],[0,0],[0,0],[0,0],[0,0],[0,0],[0,0],[0,0],[0,0],[0,0],[0,0],[0,0],[0,0],[0,0],[0,0],[0,0],[0,0],[0,0],[0,0],[0,0],[0,0],[0,0],[0,0],[0,0],[0,0],[0,0],[0,0],[0,0],[0,0],[0,0],[0,0],[0,0],[0,0],[0,0],[0,0],[0,0],[0,0],[0,0],[0,0],[0,0],[0,0],[0,0],[0,0],[0,0],[0,0],[0,0],[0,0],[0,0],[0,0],[0,0],[0,0],[0,0],[0,0],[0,0],[0,0],[0,0],[0,0],[0,0],[0,0],[0,0],[0,0],[0,0],[0,0],[0,0],[0,0],[0,0],[0,0],[0,0],[0,0],[0,0],[0,0],[0,0],[0,0],[0,0],[0,0],[0,0],[0,0],[0,0],[0,0],[0,0],[0,0],[0,0],[0,0],[0,0],[0,0],[0,0],[0,0],[0,0],[0,0],[0,0],[0,0],[0,0],[0,0],[0,0],[0,0],[0,0],[0,0],[0,0],[0,0],[0,0],[0,0],[0,0],[0,0],[0,0],[0,0],[0,0],[0,0],[0,0],[0,0],[0,0],[0,0],[0,0],[0,0],[0,0],[0,0],[0,0],[0,0],[0,0],[0,0],[0,0],[0,0],[0,0],[0,0],[0,0],[0,0],[0,0],[0,0],[0,0],[0,0],[0,0],[0,0],[0,0],[0,0],[0,0],[0,0],[0,0],[0,0],[0,0],[0,0],[0,0],[0,0],[0,0],[0,0],[0,0],[0,0],[0,0],[0,0],[0,0],[0,0],[0,0],[0,0],[0,0],[0,0],[0,0],[0,0],[0,0],[0,0],[0,0],[0,0],[0,0],[0,0],[0,0],[0,0],[0,0],[0,0],[0,0],[0,0],[0,0],[0,0],[0,0],[0,0],[0,0],[0,0],[0,0],[0,0],[0,0],[0,0],[0,0],[0,0],[0,0],[0,0],[0,0],[0,0],[0,0],[0,0],[0,0],[0,0],[0,0],[0,0],[0,0],[0,0],[0,0],[0,0],[0,0],[0,0],[0,0],[0,0],[0,0],[0,0],[0,0],[0,0],[0,0],[0,0],[0,0],[0,0],[0,0],[0,0],[0,0],[0,0],[0,0],[0,0],[0,0],[0,0],[0,0],[0,0],[0,0],[0,0],[0,0],[0,0],[0,0],[0,0],[0,0],[0,0],[0,0],[0,0],[0,0],[0,0],[0,0],[0,0],[0,0],[0,0],[0,0],[0,0],[0,0],[0,0],[0,0],[0,0],[0,0],[0,0],[0,0],[0,0],[0,0],[0,0],[0,0],[0,0],[0,0],[0,0],[0,0],[0,0],[0,0],[0,0],[0,0],[0,0],[0,0],[0,0],[0,0],[0,0],[0,0],[0,0],[0,0],[0,0],[0,0],[0,0],[0,0],[0,0],[0,0],[0,0],[0,0],[0,0],[0,0],[0,0],[0,0],[0,0],[0,0],[0,0],[0,0],[0,0],[0,0],[0,0],[0,0],[0,0],[0,0],[0,0],[0,0],[0,0],[0,0],[0,0],[0,0],[0,0],[0,0],[0,0],[0,0],[0,0],[0,0],[0,0],[0,0],[0,0],[0,0],[0,0],[0,0],[0,0],[0,0],[0,0],[0,0],[0,0],[0,0],[0,0],[0,0],[0,0],[0,0],[0,0],[0,0],[0,0],[0,0],[0,0],[0,0],[0,0],[0,0],[0,0],[0,0],[0,0],[0,0],[0,0],[0,0],[0,0],[0,0],[0,0],[0,0],[0,0],[0,0],[0,0],[0,0],[0,0],[0,0],[0,0],[0,0],[0,0],[0,0],[0,0],[0,0],[0,0],[0,0],[0,0],[0,0],[0,0],[0,0],[0,0],[0,0],[0,0],[0,0],[0,0],[0,0],[0,0],[0,0],[0,0],[0,0],[0,0],[0,0],[0,0],[0,0],[0,0],[0,0],[0,0],[0,0],[0,0],[0,0],[0,0],[0,0],[0,0],[0,0],[0,0],[0,0],[0,0],[0,0],[0,0]],"o":[[0,0],[0,0],[0,0],[0,0],[0,0],[0,0],[0,0],[0,0],[0,0],[0,0],[0,0],[0,0],[0,0],[0,0],[0,0],[0,0],[0,0],[0,0],[0,0],[0,0],[0,0],[0,0],[0,0],[0,0],[0,0],[0,0],[0,0],[0,0],[0,0],[0,0],[0,0],[0,0],[0,0],[0,0],[0,0],[0,0],[0,0],[0,0],[0,0],[0,0],[0,0],[0,0],[0,0],[0,0],[0,0],[0,0],[0,0],[0,0],[0,0],[0,0],[0,0],[0,0],[0,0],[0,0],[0,0],[0,0],[0,0],[0,0],[0,0],[0,0],[0,0],[0,0],[0,0],[0,0],[0,0],[0,0],[0,0],[0,0],[0,0],[0,0],[0,0],[0,0],[0,0],[0,0],[0,0],[0,0],[0,0],[0,0],[0,0],[0,0],[0,0],[0,0],[0,0],[0,0],[0,0],[0,0],[0,0],[0,0],[0,0],[0,0],[0,0],[0,0],[0,0],[0,0],[0,0],[0,0],[0,0],[0,0],[0,0],[0,0],[0,0],[0,0],[0,0],[0,0],[0,0],[0,0],[0,0],[0,0],[0,0],[0,0],[0,0],[0,0],[0,0],[0,0],[0,0],[0,0],[0,0],[0,0],[0,0],[0,0],[0,0],[0,0],[0,0],[0,0],[0,0],[0,0],[0,0],[0,0],[0,0],[0,0],[0,0],[0,0],[0,0],[0,0],[0,0],[0,0],[0,0],[0,0],[0,0],[0,0],[0,0],[0,0],[0,0],[0,0],[0,0],[0,0],[0,0],[0,0],[0,0],[0,0],[0,0],[0,0],[0,0],[0,0],[0,0],[0,0],[0,0],[0,0],[0,0],[0,0],[0,0],[0,0],[0,0],[0,0],[0,0],[0,0],[0,0],[0,0],[0,0],[0,0],[0,0],[0,0],[0,0],[0,0],[0,0],[0,0],[0,0],[0,0],[0,0],[0,0],[0,0],[0,0],[0,0],[0,0],[0,0],[0,0],[0,0],[0,0],[0,0],[0,0],[0,0],[0,0],[0,0],[0,0],[0,0],[0,0],[0,0],[0,0],[0,0],[0,0],[0,0],[0,0],[0,0],[0,0],[0,0],[0,0],[0,0],[0,0],[0,0],[0,0],[0,0],[0,0],[0,0],[0,0],[0,0],[0,0],[0,0],[0,0],[0,0],[0,0],[0,0],[0,0],[0,0],[0,0],[0,0],[0,0],[0,0],[0,0],[0,0],[0,0],[0,0],[0,0],[0,0],[0,0],[0,0],[0,0],[0,0],[0,0],[0,0],[0,0],[0,0],[0,0],[0,0],[0,0],[0,0],[0,0],[0,0],[0,0],[0,0],[0,0],[0,0],[0,0],[0,0],[0,0],[0,0],[0,0],[0,0],[0,0],[0,0],[0,0],[0,0],[0,0],[0,0],[0,0],[0,0],[0,0],[0,0],[0,0],[0,0],[0,0],[0,0],[0,0],[0,0],[0,0],[0,0],[0,0],[0,0],[0,0],[0,0],[0,0],[0,0],[0,0],[0,0],[0,0],[0,0],[0,0],[0,0],[0,0],[0,0],[0,0],[0,0],[0,0],[0,0],[0,0],[0,0],[0,0],[0,0],[0,0],[0,0],[0,0],[0,0],[0,0],[0,0],[0,0],[0,0],[0,0],[0,0],[0,0],[0,0],[0,0],[0,0],[0,0],[0,0],[0,0],[0,0],[0,0],[0,0],[0,0],[0,0],[0,0],[0,0],[0,0],[0,0],[0,0],[0,0],[0,0],[0,0],[0,0],[0,0],[0,0],[0,0],[0,0],[0,0],[0,0],[0,0],[0,0],[0,0],[0,0],[0,0],[0,0],[0,0],[0,0],[0,0],[0,0],[0,0],[0,0],[0,0],[0,0],[0,0],[0,0],[0,0],[0,0],[0,0],[0,0],[0,0],[0,0],[0,0],[0,0],[0,0],[0,0],[0,0],[0,0],[0,0],[0,0],[0,0],[0,0],[0,0],[0,0],[0,0],[0,0],[0,0],[0,0],[0,0],[0,0],[0,0],[0,0],[0,0],[0,0],[0,0],[0,0],[0,0],[0,0],[0,0],[0,0],[0,0],[0,0],[0,0],[0,0],[0,0],[0,0],[0,0],[0,0],[0,0],[0,0],[0,0],[0,0],[0,0],[0,0],[0,0],[0,0],[0,0],[0,0],[0,0],[0,0],[0,0],[0,0],[0,0],[0,0],[0,0],[0,0],[0,0],[0,0],[0,0],[0,0],[0,0],[0,0],[0,0],[0,0],[0,0],[0,0],[0,0],[0,0],[0,0],[0,0],[0,0],[0,0],[0,0],[0,0],[0,0],[0,0],[0,0],[0,0],[0,0],[0,0],[0,0],[0,0],[0,0],[0,0],[0,0],[0,0],[0,0],[0,0],[0,0],[0,0],[0,0],[0,0],[0,0],[0,0],[0,0],[0,0],[0,0],[0,0],[0,0],[0,0],[0,0],[0,0],[0,0],[0,0],[0,0],[0,0],[0,0],[0,0],[0,0],[0,0],[0,0],[0,0],[0,0],[0,0],[0,0],[0,0],[0,0],[0,0],[0,0],[0,0],[0,0],[0,0],[0,0],[0,0],[0,0],[0,0],[0,0],[0,0],[0,0],[0,0],[0,0],[0,0],[0,0],[0,0],[0,0],[0,0],[0,0],[0,0],[0,0],[0,0],[0,0],[0,0],[0,0],[0,0],[0,0],[0,0],[0,0],[0,0],[0,0],[0,0],[0,0],[0,0],[0,0],[0,0],[0,0],[0,0],[0,0],[0,0],[0,0],[0,0],[0,0],[0,0],[0,0],[0,0],[0,0],[0,0],[0,0],[0,0],[0,0],[0,0],[0,0],[0,0],[0,0],[0,0],[0,0],[0,0],[0,0],[0,0],[0,0],[0,0],[0,0],[0,0],[0,0],[0,0],[0,0],[0,0],[0,0],[0,0],[0,0],[0,0],[0,0],[0,0],[0,0],[0,0],[0,0],[0,0],[0,0],[0,0],[0,0],[0,0],[0,0],[0,0],[0,0],[0,0],[0,0],[0,0],[0,0],[0,0],[0,0],[0,0],[0,0],[0,0],[0,0],[0,0],[0,0],[0,0],[0,0],[0,0],[0,0],[0,0],[0,0],[0,0],[0,0],[0,0],[0,0],[0,0],[0,0],[0,0],[0,0],[0,0],[0,0],[0,0],[0,0],[0,0],[0,0],[0,0],[0,0],[0,0],[0,0],[0,0],[0,0],[0,0],[0,0],[0,0],[0,0],[0,0],[0,0],[0,0],[0,0],[0,0],[0,0],[0,0],[0,0],[0,0],[0,0],[0,0],[0,0],[0,0],[0,0],[0,0],[0,0],[0,0],[0,0],[0,0],[0,0],[0,0],[0,0],[0,0],[0,0],[0,0],[0,0],[0,0],[0,0],[0,0],[0,0],[0,0],[0,0],[0,0],[0,0],[0,0],[0,0],[0,0],[0,0],[0,0],[0,0],[0,0],[0,0],[0,0],[0,0],[0,0],[0,0],[0,0],[0,0],[0,0],[0,0],[0,0],[0,0],[0,0],[0,0],[0,0],[0,0],[0,0],[0,0],[0,0],[0,0],[0,0],[0,0],[0,0],[0,0],[0,0],[0,0],[0,0],[0,0],[0,0],[0,0],[0,0],[0,0],[0,0],[0,0],[0,0],[0,0],[0,0],[0,0],[0,0],[0,0],[0,0],[0,0],[0,0],[0,0],[0,0],[0,0],[0,0],[0,0],[0,0],[0,0],[0,0],[0,0],[0,0],[0,0],[0,0],[0,0],[0,0],[0,0],[0,0],[0,0],[0,0],[0,0],[0,0],[0,0],[0,0],[0,0],[0,0],[0,0],[0,0],[0,0],[0,0],[0,0],[0,0],[0,0],[0,0],[0,0],[0,0],[0,0],[0,0],[0,0],[0,0],[0,0],[0,0],[0,0],[0,0],[0,0],[0,0],[0,0],[0,0],[0,0],[0,0],[0,0],[0,0],[0,0],[0,0],[0,0],[0,0],[0,0],[0,0],[0,0],[0,0],[0,0],[0,0],[0,0],[0,0],[0,0],[0,0],[0,0],[0,0],[0,0],[0,0],[0,0],[0,0],[0,0],[0,0],[0,0],[0,0],[0,0],[0,0],[0,0],[0,0],[0,0],[0,0],[0,0],[0,0],[0,0],[0,0],[0,0],[0,0],[0,0],[0,0],[0,0],[0,0],[0,0],[0,0],[0,0],[0,0],[0,0],[0,0],[0,0],[0,0],[0,0],[0,0],[0,0],[0,0],[0,0],[0,0],[0,0],[0,0],[0,0],[0,0],[0,0],[0,0],[0,0],[0,0],[0,0],[0,0],[0,0],[0,0],[0,0],[0,0],[0,0],[0,0],[0,0],[0,0],[0,0],[0,0],[0,0],[0,0],[0,0],[0,0],[0,0],[0,0],[0,0],[0,0],[0,0],[0,0],[0,0],[0,0],[0,0],[0,0],[0,0],[0,0],[0,0],[0,0],[0,0],[0,0],[0,0],[0,0],[0,0],[0,0],[0,0],[0,0],[0,0],[0,0],[0,0],[0,0],[0,0],[0,0],[0,0],[0,0],[0,0],[0,0],[0,0],[0,0],[0,0],[0,0],[0,0],[0,0],[0,0],[0,0],[0,0],[0,0],[0,0],[0,0],[0,0],[0,0],[0,0],[0,0],[0,0],[0,0],[0,0],[0,0],[0,0],[0,0],[0,0],[0,0],[0,0],[0,0],[0,0],[0,0],[0,0],[0,0],[0,0],[0,0],[0,0],[0,0],[0,0],[0,0],[0,0],[0,0],[0,0],[0,0],[0,0],[0,0],[0,0],[0,0],[0,0],[0,0],[0,0],[0,0],[0,0],[0,0],[0,0],[0,0],[0,0],[0,0],[0,0],[0,0],[0,0],[0,0],[0,0],[0,0],[0,0],[0,0],[0,0],[0,0],[0,0],[0,0],[0,0],[0,0],[0,0],[0,0],[0,0],[0,0],[0,0],[0,0],[0,0],[0,0],[0,0],[0,0],[0,0],[0,0],[0,0],[0,0],[0,0],[0,0],[0,0],[0,0],[0,0],[0,0],[0,0],[0,0],[0,0],[0,0],[0,0],[0,0],[0,0],[0,0],[0,0],[0,0],[0,0],[0,0],[0,0],[0,0],[0,0],[0,0],[0,0],[0,0],[0,0],[0,0],[0,0],[0,0],[0,0],[0,0],[0,0],[0,0],[0,0],[0,0],[0,0],[0,0],[0,0],[0,0],[0,0],[0,0],[0,0],[0,0],[0,0],[0,0],[0,0],[0,0],[0,0],[0,0],[0,0],[0,0],[0,0],[0,0],[0,0],[0,0],[0,0],[0,0],[0,0],[0,0],[0,0],[0,0],[0,0],[0,0],[0,0],[0,0],[0,0],[0,0],[0,0],[0,0],[0,0],[0,0],[0,0],[0,0],[0,0],[0,0],[0,0],[0,0],[0,0],[0,0],[0,0],[0,0],[0,0],[0,0],[0,0],[0,0],[0,0],[0,0],[0,0],[0,0],[0,0],[0,0],[0,0],[0,0],[0,0],[0,0],[0,0],[0,0],[0,0],[0,0],[0,0],[0,0],[0,0],[0,0],[0,0],[0,0],[0,0],[0,0],[0,0],[0,0],[0,0],[0,0],[0,0],[0,0],[0,0],[0,0],[0,0],[0,0],[0,0],[0,0],[0,0],[0,0],[0,0],[0,0],[0,0],[0,0],[0,0],[0,0],[0,0],[0,0],[0,0],[0,0],[0,0],[0,0],[0,0],[0,0],[0,0],[0,0],[0,0],[0,0],[0,0],[0,0],[0,0],[0,0],[0,0],[0,0],[0,0],[0,0],[0,0],[0,0],[0,0],[0,0],[0,0],[0,0],[0,0],[0,0],[0,0],[0,0],[0,0],[0,0],[0,0],[0,0],[0,0],[0,0],[0,0],[0,0],[0,0],[0,0],[0,0],[0,0],[0,0],[0,0],[0,0],[0,0],[0,0],[0,0],[0,0],[0,0],[0,0],[0,0],[0,0],[0,0],[0,0],[0,0],[0,0],[0,0],[0,0],[0,0],[0,0],[0,0],[0,0],[0,0],[0,0],[0,0],[0,0],[0,0],[0,0],[0,0],[0,0],[0,0],[0,0],[0,0],[0,0],[0,0],[0,0],[0,0],[0,0],[0,0],[0,0],[0,0],[0,0],[0,0],[0,0],[0,0],[0,0],[0,0],[0,0],[0,0],[0,0],[0,0],[0,0],[0,0],[0,0],[0,0],[0,0],[0,0],[0,0],[0,0],[0,0],[0,0],[0,0],[0,0],[0,0],[0,0],[0,0],[0,0],[0,0],[0,0],[0,0],[0,0],[0,0],[0,0],[0,0],[0,0],[0,0],[0,0],[0,0],[0,0],[0,0],[0,0],[0,0],[0,0],[0,0],[0,0],[0,0],[0,0],[0,0],[0,0],[0,0],[0,0],[0,0],[0,0],[0,0],[0,0],[0,0],[0,0],[0,0],[0,0],[0,0],[0,0]],"v":[[51.791,-73.099],[51.876,-73.099],[51.958,-73.098],[52.043,-73.097],[52.128,-73.096],[52.211,-73.095],[52.295,-73.093],[52.38,-73.091],[52.462,-73.089],[52.546,-73.086],[52.63,-73.083],[52.715,-73.08],[52.798,-73.077],[52.882,-73.073],[52.967,-73.069],[53.05,-73.065],[53.132,-73.061],[53.215,-73.056],[53.299,-73.052],[53.384,-73.046],[53.465,-73.041],[53.549,-73.035],[53.633,-73.029],[53.714,-73.023],[53.799,-73.017],[53.883,-73.01],[53.965,-73.003],[54.048,-72.996],[54.13,-72.988],[54.212,-72.981],[54.296,-72.973],[54.378,-72.964],[54.461,-72.956],[54.543,-72.947],[54.625,-72.938],[54.708,-72.929],[54.79,-72.919],[54.872,-72.909],[54.954,-72.899],[55.036,-72.889],[55.118,-72.878],[55.202,-72.867],[55.282,-72.856],[55.364,-72.845],[55.447,-72.833],[55.526,-72.822],[55.609,-72.81],[55.691,-72.797],[55.771,-72.785],[55.859,-72.771],[56.015,-72.746],[56.177,-72.718],[56.34,-72.69],[56.502,-72.66],[56.661,-72.63],[56.823,-72.598],[56.983,-72.566],[57.144,-72.533],[57.304,-72.498],[57.463,-72.463],[57.623,-72.427],[57.78,-72.39],[57.939,-72.352],[58.098,-72.313],[58.254,-72.273],[58.412,-72.231],[58.57,-72.189],[58.726,-72.146],[58.882,-72.103],[59.038,-72.058],[59.192,-72.012],[59.347,-71.965],[59.502,-71.918],[59.656,-71.869],[59.81,-71.82],[59.963,-71.77],[60.118,-71.718],[60.27,-71.666],[60.42,-71.613],[60.571,-71.559],[60.723,-71.504],[60.874,-71.448],[61.024,-71.392],[61.174,-71.334],[61.323,-71.276],[61.473,-71.216],[61.622,-71.156],[61.77,-71.095],[61.917,-71.033],[62.064,-70.97],[62.212,-70.907],[62.357,-70.842],[62.502,-70.777],[62.647,-70.711],[62.792,-70.644],[62.937,-70.575],[63.081,-70.507],[63.223,-70.437],[63.367,-70.367],[63.509,-70.296],[63.65,-70.224],[63.791,-70.151],[63.932,-70.077],[64.072,-70.002],[64.211,-69.927],[64.351,-69.851],[64.49,-69.774],[64.627,-69.696],[64.765,-69.618],[64.904,-69.538],[65.039,-69.457],[65.174,-69.377],[65.31,-69.295],[65.446,-69.213],[65.58,-69.129],[65.713,-69.045],[65.847,-68.96],[65.98,-68.874],[66.111,-68.788],[66.243,-68.701],[66.374,-68.613],[66.505,-68.524],[66.634,-68.435],[66.764,-68.344],[66.894,-68.253],[67.02,-68.162],[67.147,-68.07],[67.275,-67.976],[67.403,-67.882],[67.527,-67.788],[67.652,-67.693],[67.776,-67.596],[67.901,-67.499],[68.024,-67.401],[68.147,-67.304],[68.269,-67.204],[68.391,-67.105],[68.511,-67.004],[68.631,-66.904],[68.751,-66.802],[68.871,-66.699],[68.989,-66.595],[69.107,-66.492],[69.224,-66.387],[69.34,-66.282],[69.456,-66.176],[69.572,-66.069],[69.686,-65.962],[69.801,-65.853],[69.914,-65.745],[70.025,-65.636],[70.139,-65.526],[70.249,-65.415],[70.36,-65.304],[70.47,-65.192],[70.581,-65.079],[70.688,-64.965],[70.796,-64.852],[70.904,-64.737],[71.011,-64.621],[71.116,-64.507],[71.223,-64.389],[71.327,-64.272],[71.431,-64.155],[71.533,-64.036],[71.636,-63.917],[71.737,-63.797],[71.839,-63.677],[71.94,-63.556],[72.04,-63.435],[72.138,-63.312],[72.237,-63.19],[72.333,-63.067],[72.431,-62.942],[72.527,-62.817],[72.623,-62.693],[72.716,-62.567],[72.812,-62.44],[72.905,-62.313],[72.996,-62.186],[73.088,-62.057],[73.18,-61.929],[73.269,-61.8],[73.359,-61.67],[73.447,-61.54],[73.536,-61.409],[73.623,-61.277],[73.709,-61.145],[73.796,-61.012],[73.879,-60.879],[73.963,-60.745],[74.047,-60.61],[74.13,-60.476],[74.212,-60.34],[74.292,-60.205],[74.372,-60.069],[74.452,-59.931],[74.531,-59.793],[74.609,-59.655],[74.685,-59.517],[74.762,-59.377],[74.837,-59.238],[74.911,-59.098],[74.985,-58.957],[75.058,-58.815],[75.13,-58.673],[75.201,-58.532],[75.272,-58.389],[75.341,-58.246],[75.411,-58.103],[75.478,-57.958],[75.546,-57.811],[75.612,-57.668],[75.677,-57.522],[75.742,-57.375],[75.805,-57.229],[75.868,-57.082],[75.931,-56.935],[75.991,-56.787],[76.051,-56.638],[76.11,-56.489],[76.169,-56.339],[76.226,-56.19],[76.284,-56.04],[76.339,-55.888],[76.395,-55.737],[76.448,-55.586],[76.5,-55.435],[76.553,-55.282],[76.604,-55.129],[76.655,-54.976],[76.704,-54.821],[76.752,-54.667],[76.8,-54.513],[76.848,-54.358],[76.893,-54.203],[76.937,-54.047],[76.982,-53.891],[77.024,-53.734],[77.067,-53.577],[77.108,-53.42],[77.147,-53.262],[77.186,-53.104],[77.224,-52.946],[77.261,-52.788],[77.298,-52.628],[77.333,-52.469],[77.368,-52.309],[77.401,-52.149],[77.433,-51.988],[77.464,-51.827],[77.495,-51.666],[77.524,-51.506],[77.554,-51.343],[77.58,-51.18],[77.605,-51.025],[77.619,-50.937],[77.632,-50.857],[77.644,-50.775],[77.656,-50.691],[77.669,-50.611],[77.68,-50.53],[77.691,-50.448],[77.702,-50.368],[77.713,-50.284],[77.723,-50.201],[77.734,-50.12],[77.744,-50.037],[77.754,-49.956],[77.763,-49.873],[77.773,-49.791],[77.781,-49.709],[77.791,-49.627],[77.799,-49.542],[77.807,-49.46],[77.815,-49.378],[77.823,-49.296],[77.83,-49.213],[77.837,-49.131],[77.844,-49.049],[77.851,-48.964],[77.858,-48.879],[77.864,-48.799],[77.87,-48.717],[77.875,-48.63],[77.881,-48.548],[77.886,-48.465],[77.891,-48.382],[77.895,-48.3],[77.9,-48.213],[77.904,-48.131],[77.908,-48.048],[77.911,-47.963],[77.915,-47.881],[77.918,-47.796],[77.921,-47.711],[77.923,-47.628],[77.925,-47.546],[77.927,-47.461],[77.929,-47.376],[77.932,-47.294],[77.932,-47.209],[77.933,-47.124],[77.933,-47.041],[77.934,-46.956],[77.934,-46.878],[77.934,46.877],[77.934,46.956],[77.933,47.041],[77.933,47.123],[77.932,47.208],[77.932,47.293],[77.929,47.376],[77.927,47.46],[77.925,47.545],[77.923,47.628],[77.921,47.711],[77.918,47.795],[77.915,47.88],[77.911,47.963],[77.908,48.047],[77.904,48.13],[77.9,48.213],[77.895,48.299],[77.891,48.382],[77.886,48.464],[77.881,48.547],[77.875,48.63],[77.87,48.716],[77.864,48.798],[77.858,48.879],[77.851,48.963],[77.844,49.047],[77.837,49.13],[77.83,49.212],[77.823,49.295],[77.815,49.377],[77.807,49.46],[77.799,49.542],[77.791,49.626],[77.781,49.708],[77.773,49.79],[77.763,49.872],[77.754,49.955],[77.744,50.037],[77.734,50.119],[77.723,50.201],[77.713,50.283],[77.702,50.367],[77.691,50.447],[77.68,50.529],[77.669,50.611],[77.656,50.69],[77.644,50.774],[77.632,50.856],[77.619,50.936],[77.605,51.024],[77.58,51.18],[77.554,51.342],[77.524,51.505],[77.495,51.666],[77.464,51.826],[77.433,51.988],[77.401,52.148],[77.368,52.308],[77.333,52.468],[77.298,52.627],[77.261,52.787],[77.224,52.946],[77.186,53.104],[77.147,53.261],[77.108,53.419],[77.067,53.577],[77.024,53.734],[76.982,53.891],[76.937,54.046],[76.893,54.202],[76.848,54.357],[76.8,54.513],[76.752,54.666],[76.704,54.82],[76.655,54.975],[76.604,55.128],[76.553,55.282],[76.5,55.434],[76.448,55.585],[76.395,55.737],[76.339,55.888],[76.284,56.039],[76.226,56.189],[76.169,56.339],[76.11,56.488],[76.051,56.637],[75.991,56.787],[75.931,56.934],[75.868,57.081],[75.805,57.229],[75.742,57.376],[75.677,57.521],[75.612,57.667],[75.545,57.812],[75.478,57.957],[75.411,58.102],[75.341,58.246],[75.272,58.387],[75.202,58.531],[75.13,58.673],[75.058,58.815],[74.985,58.957],[74.911,59.097],[74.837,59.237],[74.762,59.376],[74.685,59.516],[74.609,59.655],[74.531,59.793],[74.452,59.93],[74.372,60.067],[74.292,60.204],[74.212,60.34],[74.13,60.475],[74.049,60.609],[73.963,60.745],[73.879,60.879],[73.796,61.011],[73.709,61.144],[73.623,61.276],[73.536,61.407],[73.447,61.54],[73.359,61.669],[73.269,61.799],[73.18,61.929],[73.088,62.057],[72.996,62.186],[72.903,62.313],[72.81,62.44],[72.717,62.566],[72.623,62.691],[72.527,62.817],[72.431,62.941],[72.334,63.065],[72.237,63.189],[72.138,63.312],[72.04,63.434],[71.939,63.555],[71.839,63.676],[71.737,63.797],[71.636,63.916],[71.533,64.035],[71.431,64.154],[71.325,64.273],[71.223,64.389],[71.116,64.505],[71.01,64.622],[70.904,64.735],[70.796,64.851],[70.687,64.966],[70.581,65.078],[70.47,65.191],[70.36,65.303],[70.25,65.414],[70.139,65.525],[70.026,65.635],[69.913,65.745],[69.801,65.853],[69.686,65.961],[69.572,66.068],[69.456,66.176],[69.34,66.282],[69.224,66.386],[69.107,66.492],[68.989,66.595],[68.871,66.697],[68.752,66.8],[68.632,66.902],[68.511,67.004],[68.39,67.104],[68.268,67.204],[68.147,67.303],[68.024,67.401],[67.901,67.498],[67.778,67.595],[67.652,67.692],[67.529,67.786],[67.401,67.882],[67.274,67.976],[67.148,68.069],[67.02,68.162],[66.894,68.252],[66.764,68.343],[66.634,68.434],[66.504,68.524],[66.374,68.613],[66.243,68.7],[66.112,68.787],[65.98,68.873],[65.847,68.96],[65.712,69.045],[65.58,69.128],[65.446,69.212],[65.311,69.294],[65.175,69.376],[65.038,69.458],[64.904,69.537],[64.767,69.616],[64.629,69.695],[64.489,69.774],[64.351,69.85],[64.212,69.926],[64.072,70.002],[63.932,70.076],[63.791,70.15],[63.651,70.223],[63.509,70.295],[63.367,70.366],[63.223,70.437],[63.081,70.507],[62.936,70.575],[62.792,70.643],[62.648,70.71],[62.502,70.777],[62.357,70.842],[62.212,70.906],[62.064,70.97],[61.917,71.032],[61.77,71.095],[61.622,71.156],[61.474,71.215],[61.322,71.276],[61.173,71.334],[61.025,71.391],[60.875,71.447],[60.723,71.504],[60.572,71.558],[60.421,71.612],[60.268,71.666],[60.115,71.718],[59.963,71.769],[59.811,71.819],[59.658,71.869],[59.502,71.917],[59.347,71.965],[59.192,72.011],[59.038,72.057],[58.882,72.102],[58.724,72.146],[58.568,72.19],[58.412,72.231],[58.255,72.272],[58.099,72.311],[57.939,72.351],[57.779,72.39],[57.621,72.426],[57.464,72.462],[57.304,72.498],[57.142,72.532],[56.982,72.566],[56.825,72.598],[56.663,72.629],[56.502,72.66],[56.338,72.689],[56.177,72.717],[56.016,72.745],[55.859,72.77],[55.771,72.784],[55.689,72.797],[55.607,72.809],[55.53,72.821],[55.448,72.833],[55.362,72.845],[55.28,72.856],[55.202,72.867],[55.12,72.877],[55.035,72.888],[54.957,72.898],[54.874,72.908],[54.788,72.919],[54.706,72.928],[54.627,72.937],[54.545,72.946],[54.46,72.955],[54.378,72.965],[54.296,72.972],[54.212,72.98],[54.13,72.988],[54.048,72.995],[53.965,73.002],[53.883,73.009],[53.8,73.016],[53.714,73.023],[53.632,73.029],[53.549,73.036],[53.466,73.04],[53.384,73.046],[53.297,73.051],[53.215,73.057],[53.132,73.061],[53.05,73.065],[52.967,73.069],[52.88,73.073],[52.798,73.076],[52.715,73.08],[52.633,73.084],[52.551,73.085],[52.462,73.088],[52.377,73.09],[52.293,73.092],[52.214,73.094],[52.128,73.095],[52.041,73.097],[51.958,73.098],[51.876,73.098],[51.79,73.099],[51.71,73.099],[-51.711,73.099],[-51.79,73.099],[-51.877,73.098],[-51.96,73.098],[-52.042,73.097],[-52.128,73.095],[-52.215,73.094],[-52.295,73.092],[-52.377,73.09],[-52.464,73.088],[-52.551,73.085],[-52.632,73.084],[-52.716,73.08],[-52.799,73.076],[-52.882,73.073],[-52.968,73.069],[-53.05,73.065],[-53.132,73.061],[-53.215,73.057],[-53.298,73.051],[-53.385,73.046],[-53.468,73.04],[-53.55,73.036],[-53.633,73.029],[-53.715,73.023],[-53.801,73.016],[-53.883,73.009],[-53.965,73.002],[-54.049,72.995],[-54.131,72.988],[-54.213,72.98],[-54.295,72.972],[-54.378,72.965],[-54.46,72.955],[-54.546,72.946],[-54.629,72.937],[-54.706,72.928],[-54.788,72.919],[-54.874,72.908],[-54.956,72.898],[-55.035,72.888],[-55.12,72.877],[-55.202,72.867],[-55.281,72.856],[-55.363,72.845],[-55.449,72.833],[-55.531,72.821],[-55.609,72.809],[-55.689,72.797],[-55.771,72.784],[-55.86,72.77],[-56.017,72.745],[-56.178,72.717],[-56.339,72.689],[-56.502,72.66],[-56.663,72.629],[-56.825,72.598],[-56.982,72.566],[-57.143,72.532],[-57.304,72.498],[-57.465,72.462],[-57.622,72.426],[-57.78,72.389],[-57.939,72.351],[-58.1,72.311],[-58.256,72.271],[-58.412,72.231],[-58.568,72.19],[-58.725,72.146],[-58.883,72.102],[-59.037,72.057],[-59.193,72.011],[-59.348,71.965],[-59.502,71.917],[-59.658,71.868],[-59.812,71.819],[-59.964,71.769],[-60.115,71.718],[-60.269,71.666],[-60.421,71.612],[-60.572,71.558],[-60.723,71.504],[-60.876,71.447],[-61.026,71.391],[-61.174,71.334],[-61.324,71.275],[-61.475,71.215],[-61.622,71.156],[-61.77,71.095],[-61.919,71.032],[-62.064,70.97],[-62.212,70.906],[-62.357,70.842],[-62.502,70.777],[-62.649,70.71],[-62.792,70.643],[-62.937,70.575],[-63.08,70.506],[-63.224,70.437],[-63.367,70.366],[-63.51,70.295],[-63.652,70.222],[-63.791,70.15],[-63.933,70.076],[-64.073,70.002],[-64.214,69.926],[-64.352,69.85],[-64.489,69.774],[-64.629,69.695],[-64.766,69.616],[-64.904,69.537],[-65.039,69.458],[-65.176,69.376],[-65.312,69.294],[-65.446,69.212],[-65.581,69.128],[-65.714,69.045],[-65.847,68.959],[-65.981,68.873],[-66.113,68.787],[-66.244,68.7],[-66.375,68.612],[-66.505,68.524],[-66.633,68.435],[-66.766,68.343],[-66.894,68.252],[-67.021,68.162],[-67.149,68.069],[-67.275,67.976],[-67.402,67.882],[-67.527,67.787],[-67.653,67.692],[-67.779,67.595],[-67.902,67.498],[-68.025,67.401],[-68.148,67.303],[-68.269,67.204],[-68.392,67.104],[-68.512,67.004],[-68.633,66.903],[-68.753,66.8],[-68.873,66.697],[-68.989,66.595],[-69.107,66.492],[-69.225,66.386],[-69.342,66.281],[-69.457,66.176],[-69.572,66.068],[-69.687,65.961],[-69.8,65.853],[-69.915,65.744],[-70.028,65.635],[-70.139,65.525],[-70.251,65.414],[-70.36,65.303],[-70.471,65.191],[-70.58,65.078],[-70.689,64.966],[-70.796,64.851],[-70.905,64.736],[-71.011,64.622],[-71.117,64.505],[-71.223,64.389],[-71.326,64.273],[-71.431,64.154],[-71.535,64.034],[-71.636,63.917],[-71.739,63.797],[-71.839,63.676],[-71.94,63.556],[-72.041,63.433],[-72.139,63.312],[-72.236,63.189],[-72.334,63.065],[-72.432,62.941],[-72.528,62.817],[-72.623,62.692],[-72.717,62.566],[-72.811,62.44],[-72.904,62.313],[-72.998,62.185],[-73.089,62.058],[-73.18,61.929],[-73.27,61.799],[-73.36,61.669],[-73.449,61.539],[-73.537,61.407],[-73.623,61.276],[-73.71,61.144],[-73.796,61.011],[-73.88,60.879],[-73.964,60.745],[-74.048,60.61],[-74.131,60.475],[-74.212,60.34],[-74.294,60.203],[-74.374,60.067],[-74.452,59.931],[-74.532,59.793],[-74.609,59.655],[-74.687,59.516],[-74.762,59.376],[-74.838,59.237],[-74.912,59.097],[-74.986,58.956],[-75.059,58.815],[-75.131,58.674],[-75.204,58.531],[-75.273,58.387],[-75.342,58.245],[-75.411,58.101],[-75.479,57.957],[-75.545,57.813],[-75.613,57.667],[-75.678,57.521],[-75.742,57.376],[-75.805,57.229],[-75.869,57.081],[-75.931,56.933],[-75.992,56.786],[-76.051,56.637],[-76.111,56.488],[-76.17,56.339],[-76.226,56.189],[-76.284,56.039],[-76.338,55.889],[-76.394,55.738],[-76.449,55.585],[-76.502,55.433],[-76.554,55.281],[-76.605,55.129],[-76.656,54.975],[-76.705,54.82],[-76.752,54.667],[-76.801,54.513],[-76.848,54.357],[-76.893,54.202],[-76.938,54.046],[-76.982,53.89],[-77.025,53.734],[-77.067,53.578],[-77.108,53.419],[-77.148,53.261],[-77.187,53.104],[-77.225,52.946],[-77.261,52.787],[-77.299,52.626],[-77.334,52.468],[-77.368,52.309],[-77.402,52.148],[-77.433,51.987],[-77.465,51.826],[-77.495,51.666],[-77.524,51.504],[-77.554,51.343],[-77.581,51.181],[-77.606,51.024],[-77.619,50.936],[-77.633,50.854],[-77.644,50.774],[-77.657,50.692],[-77.669,50.611],[-77.68,50.529],[-77.692,50.447],[-77.702,50.365],[-77.714,50.283],[-77.723,50.201],[-77.734,50.119],[-77.745,50.037],[-77.755,49.955],[-77.764,49.874],[-77.774,49.79],[-77.783,49.706],[-77.791,49.626],[-77.8,49.544],[-77.808,49.46],[-77.816,49.377],[-77.824,49.295],[-77.83,49.212],[-77.838,49.13],[-77.846,49.045],[-77.852,48.963],[-77.859,48.881],[-77.865,48.796],[-77.872,48.714],[-77.876,48.632],[-77.882,48.549],[-77.887,48.464],[-77.893,48.38],[-77.896,48.297],[-77.9,48.215],[-77.904,48.13],[-77.909,48.047],[-77.912,47.965],[-77.915,47.878],[-77.92,47.795],[-77.921,47.713],[-77.924,47.628],[-77.926,47.545],[-77.929,47.46],[-77.929,47.376],[-77.932,47.291],[-77.933,47.208],[-77.934,47.125],[-77.934,47.039],[-77.934,-47.039],[-77.934,-47.126],[-77.932,-47.292],[-77.929,-47.376],[-77.929,-47.461],[-77.926,-47.546],[-77.924,-47.628],[-77.921,-47.713],[-77.915,-47.879],[-77.912,-47.965],[-77.904,-48.131],[-77.9,-48.215],[-77.896,-48.298],[-77.893,-48.38],[-77.887,-48.465],[-77.882,-48.55],[-77.877,-48.632],[-77.872,-48.715],[-77.865,-48.797],[-77.859,-48.881],[-77.852,-48.964],[-77.846,-49.047],[-77.838,-49.131],[-77.83,-49.213],[-77.824,-49.296],[-77.808,-49.46],[-77.8,-49.544],[-77.791,-49.627],[-77.783,-49.707],[-77.773,-49.791],[-77.764,-49.875],[-77.755,-49.956],[-77.745,-50.037],[-77.734,-50.12],[-77.725,-50.201],[-77.714,-50.284],[-77.68,-50.53],[-77.669,-50.611],[-77.644,-50.775],[-77.633,-50.855],[-77.606,-51.025],[-77.581,-51.181],[-77.554,-51.344],[-77.524,-51.505],[-77.495,-51.666],[-77.465,-51.827],[-77.433,-51.987],[-77.402,-52.149],[-77.368,-52.31],[-77.334,-52.469],[-77.299,-52.627],[-77.261,-52.788],[-77.225,-52.946],[-77.187,-53.104],[-77.148,-53.262],[-77.108,-53.42],[-77.067,-53.578],[-77.025,-53.734],[-76.982,-53.89],[-76.938,-54.047],[-76.893,-54.203],[-76.848,-54.358],[-76.801,-54.513],[-76.752,-54.668],[-76.705,-54.821],[-76.654,-54.976],[-76.605,-55.13],[-76.554,-55.281],[-76.502,-55.434],[-76.449,-55.586],[-76.395,-55.738],[-76.339,-55.889],[-76.284,-56.04],[-76.226,-56.19],[-76.17,-56.339],[-76.111,-56.489],[-76.051,-56.638],[-75.992,-56.785],[-75.931,-56.934],[-75.869,-57.082],[-75.805,-57.229],[-75.678,-57.522],[-75.613,-57.668],[-75.479,-57.958],[-75.411,-58.102],[-75.342,-58.245],[-75.273,-58.389],[-75.204,-58.532],[-75.131,-58.674],[-75.059,-58.815],[-74.986,-58.957],[-74.912,-59.098],[-74.838,-59.238],[-74.762,-59.377],[-74.686,-59.517],[-74.532,-59.793],[-74.452,-59.931],[-74.373,-60.069],[-74.294,-60.204],[-74.213,-60.34],[-74.131,-60.476],[-74.048,-60.611],[-73.965,-60.745],[-73.88,-60.879],[-73.796,-61.012],[-73.71,-61.145],[-73.623,-61.278],[-73.537,-61.409],[-73.449,-61.539],[-73.36,-61.67],[-73.27,-61.8],[-73.18,-61.929],[-73.089,-62.058],[-72.998,-62.186],[-72.812,-62.44],[-72.717,-62.567],[-72.623,-62.693],[-72.528,-62.817],[-72.432,-62.942],[-72.334,-63.067],[-72.236,-63.19],[-72.041,-63.434],[-71.94,-63.556],[-71.839,-63.677],[-71.739,-63.797],[-71.636,-63.917],[-71.535,-64.036],[-71.431,-64.155],[-71.223,-64.389],[-71.117,-64.507],[-71.012,-64.621],[-70.905,-64.737],[-70.796,-64.852],[-70.689,-64.965],[-70.58,-65.079],[-70.471,-65.192],[-70.36,-65.304],[-70.251,-65.415],[-70.139,-65.526],[-70.027,-65.636],[-69.915,-65.744],[-69.802,-65.853],[-69.686,-65.963],[-69.458,-66.175],[-69.342,-66.281],[-69.225,-66.387],[-69.107,-66.492],[-68.989,-66.595],[-68.872,-66.699],[-68.752,-66.802],[-68.632,-66.904],[-68.512,-67.005],[-68.392,-67.104],[-68.271,-67.204],[-68.148,-67.304],[-68.025,-67.402],[-67.902,-67.499],[-67.778,-67.596],[-67.653,-67.693],[-67.527,-67.788],[-67.403,-67.882],[-67.275,-67.976],[-67.148,-68.07],[-67.021,-68.162],[-66.894,-68.253],[-66.765,-68.344],[-66.635,-68.435],[-66.506,-68.524],[-66.376,-68.613],[-66.112,-68.789],[-65.98,-68.875],[-65.847,-68.96],[-65.715,-69.045],[-65.581,-69.129],[-65.446,-69.213],[-65.312,-69.295],[-65.176,-69.377],[-65.041,-69.457],[-64.904,-69.538],[-64.765,-69.618],[-64.629,-69.696],[-64.49,-69.774],[-64.352,-69.851],[-64.213,-69.927],[-63.933,-70.077],[-63.791,-70.151],[-63.65,-70.223],[-63.51,-70.296],[-63.224,-70.438],[-63.082,-70.507],[-62.937,-70.575],[-62.792,-70.644],[-62.648,-70.711],[-62.504,-70.777],[-62.357,-70.843],[-62.212,-70.907],[-62.066,-70.97],[-61.917,-71.033],[-61.77,-71.095],[-61.473,-71.217],[-61.325,-71.276],[-61.024,-71.392],[-60.874,-71.448],[-60.723,-71.504],[-60.572,-71.559],[-60.421,-71.613],[-60.27,-71.666],[-60.118,-71.718],[-59.964,-71.77],[-59.809,-71.82],[-59.657,-71.869],[-59.502,-71.918],[-59.348,-71.965],[-59.193,-72.012],[-59.037,-72.058],[-58.883,-72.103],[-58.727,-72.146],[-58.57,-72.189],[-58.412,-72.231],[-58.255,-72.272],[-58.097,-72.313],[-57.939,-72.352],[-57.782,-72.39],[-57.623,-72.427],[-57.464,-72.463],[-57.144,-72.533],[-56.984,-72.566],[-56.824,-72.598],[-56.662,-72.63],[-56.502,-72.66],[-56.34,-72.69],[-56.178,-72.718],[-56.016,-72.746],[-55.86,-72.771],[-55.771,-72.785],[-55.691,-72.797],[-55.611,-72.81],[-55.527,-72.822],[-55.447,-72.833],[-55.365,-72.845],[-55.283,-72.856],[-55.202,-72.867],[-55.119,-72.878],[-55.037,-72.889],[-54.873,-72.909],[-54.709,-72.929],[-54.627,-72.938],[-54.544,-72.947],[-54.462,-72.956],[-54.378,-72.964],[-54.295,-72.973],[-54.213,-72.981],[-54.131,-72.988],[-54.049,-72.996],[-53.965,-73.003],[-53.883,-73.01],[-53.8,-73.017],[-53.715,-73.023],[-53.635,-73.029],[-53.55,-73.035],[-53.466,-73.041],[-53.385,-73.046],[-53.299,-73.052],[-53.215,-73.056],[-53.132,-73.061],[-52.968,-73.069],[-52.883,-73.073],[-52.799,-73.077],[-52.716,-73.08],[-52.631,-73.083],[-52.464,-73.089],[-52.297,-73.093],[-52.212,-73.095],[-51.877,-73.099]],"c":true},"ix":2},"nm":"Caminho 1","mn":"ADBE Vector Shape - Group","hd":false},{"ind":1,"ty":"sh","ix":2,"ks":{"a":0,"k":{"i":[[0,0],[0,0],[0,0],[0,0],[0,0],[0,0],[0,0],[0,0],[0,0],[0,0],[0,0],[0,0],[0,0],[0,0],[0,0],[0,0],[0,0],[0,0],[0,0],[0,0],[0,0],[0,0],[0,0],[0,0],[0,0],[0,0],[0,0],[0,0],[0,0],[0,0],[0,0],[0,0],[0,0],[0,0],[0,0],[0,0],[0,0],[0,0],[0,0],[0,0],[0,0],[0,0],[0,0],[0,0],[0,0],[0,0],[0,0],[0,0],[0,0],[0,0],[0,0],[0,0],[0,0],[0,0],[0,0],[0,0],[0,0],[0,0],[0,0],[0,0],[0,0],[0,0],[0,0],[0,0],[0,0],[0,0],[0,0],[0,0],[0,0],[0,0],[0,0],[0,0],[0,0],[0,0],[0,0],[0,0],[0,0],[0,0],[0,0],[0,0],[0,0],[0,0],[0,0],[0,0],[0,0],[0,0],[0,0],[0,0],[0,0],[0,0],[0,0],[0,0],[0,0],[0,0],[0,0],[0,0],[0,0],[0,0],[0,0],[0,0],[0,0],[0,0],[0,0],[0,0],[0,0],[0,0],[0,0],[0,0],[0,0],[0,0],[0,0],[0,0],[0,0],[0,0],[0,0],[0,0],[0,0],[0,0],[0,0],[0,0],[0,0],[0,0],[0,0],[0,0],[0,0],[0,0],[0,0],[0,0],[0,0],[0,0],[0,0],[0,0],[0,0],[0,0],[0,0],[0,0],[0,0],[0,0],[0,0],[0,0],[0,0],[0,0],[0,0],[0,0],[0,0],[0,0],[0,0],[0,0],[0,0],[0,0],[0,0],[0,0],[0,0],[0,0],[0,0],[0,0],[0,0],[0,0],[0,0],[0,0],[0,0],[0,0],[0,0],[0,0],[0,0],[0,0],[0,0],[0,0],[0,0],[0,0],[0,0],[0,0],[0,0],[0,0],[0,0],[0,0],[0,0],[0,0],[0,0],[0,0],[0,0],[0,0],[0,0],[0,0],[0,0],[0,0],[0,0],[0,0],[0,0],[0,0],[0,0],[0,0],[0,0],[0,0],[0,0],[0,0],[0,0],[0,0],[0,0],[0,0],[0,0],[0,0],[0,0],[0,0],[0,0],[0,0],[0,0],[0,0],[0,0],[0,0],[0,0],[0,0],[0,0],[0,0],[0,0],[0,0],[0,0],[0,0],[0,0],[0,0],[0,0],[0,0],[0,0],[0,0],[0,0],[0,0],[0,0],[0,0],[0,0],[0,0],[0,0],[0,0],[0,0],[0,0],[0,0],[0,0],[0,0],[0,0],[0,0],[0,0],[0,0],[0,0],[0,0],[0,0],[0,0],[0,0],[0,0],[0,0],[0,0],[0,0],[0,0],[0,0],[0,0],[0,0],[0,0],[0,0],[0,0],[0,0],[0,0],[0,0],[0,0],[0,0],[0,0],[0,0],[0,0],[0,0],[0,0],[0,0],[0,0],[0,0],[0,0],[0,0],[0,0],[0,0],[0,0],[0,0],[0,0],[0,0],[0,0],[0,0],[0,0],[0,0],[0,0],[0,0],[0,0],[0,0],[0,0],[0,0],[0,0],[0,0],[0,0],[0,0],[0,0],[0,0],[0,0],[0,0],[0,0],[0,0],[0,0],[0,0],[0,0],[0,0],[0,0],[0,0],[0,0],[0,0],[0,0],[0,0],[0,0],[0,0],[0,0],[0,0],[0,0],[0,0],[0,0],[0,0],[0,0],[0,0],[0,0],[0,0],[0,0],[0,0],[0,0],[0,0],[0,0],[0,0],[0,0],[0,0],[0,0],[0,0],[0,0],[0,0],[0,0],[0,0],[0,0],[0,0],[0,0],[0,0],[0,0],[0,0],[0,0],[0,0],[0,0],[0,0],[0,0],[0,0],[0,0],[0,0],[0,0],[0,0],[0,0],[0,0],[0,0],[0,0],[0,0],[0,0],[0,0],[0,0],[0,0],[0,0],[0,0],[0,0],[0,0],[0,0],[0,0],[0,0],[0,0],[0,0],[0,0],[0,0],[0,0],[0,0],[0,0],[0,0],[0,0],[0,0],[0,0],[0,0],[0,0],[0,0],[0,0],[0,0],[0,0],[0,0],[0,0],[0,0],[0,0],[0,0],[0,0],[0,0],[0,0],[0,0],[0,0],[0,0],[0,0],[0,0],[0,0],[0,0],[0,0],[0,0],[0,0],[0,0],[0,0],[0,0],[0,0],[0,0],[0,0],[0,0],[0,0],[0,0],[0,0],[0,0],[0,0],[0,0],[0,0],[0,0],[0,0],[0,0],[0,0],[0,0],[0,0],[0,0],[0,0],[0,0],[0,0],[0,0],[0,0],[0,0],[0,0],[0,0],[0,0],[0,0],[0,0],[0,0],[0,0],[0,0],[0,0],[0,0],[0,0],[0,0],[0,0],[0,0],[0,0],[0,0],[0,0],[0,0],[0,0],[0,0],[0,0],[0,0],[0,0],[0,0],[0,0],[0,0],[0,0],[0,0],[0,0],[0,0],[0,0],[0,0],[0,0],[0,0],[0,0],[0,0],[0,0],[0,0],[0,0],[0,0],[0,0],[0,0],[0,0],[0,0],[0,0],[0,0],[0,0],[0,0],[0,0],[0,0],[0,0],[0,0],[0,0],[0,0],[0,0],[0,0],[0,0],[0,0],[0,0],[0,0],[0,0],[0,0],[0,0],[0,0],[0,0],[0,0],[0,0],[0,0],[0,0],[0,0],[0,0],[0,0],[0,0],[0,0],[0,0],[0,0],[0,0],[0,0],[0,0],[0,0],[0,0],[0,0],[0,0],[0,0],[0,0],[0,0],[0,0],[0,0],[0,0],[0,0],[0,0],[0,0],[0,0],[0,0],[0,0],[0,0],[0,0],[0,0],[0,0],[0,0],[0,0],[0,0],[0,0],[0,0],[0,0],[0,0],[0,0],[0,0],[0,0],[0,0],[0,0],[0,0],[0,0],[0,0],[0,0],[0,0],[0,0],[0,0],[0,0],[0,0],[0,0],[0,0],[0,0],[0,0],[0,0],[0,0],[0,0],[0,0],[0,0],[0,0],[0,0],[0,0],[0,0],[0,0],[0,0],[0,0],[0,0],[0,0],[0,0],[0,0],[0,0],[0,0],[0,0],[0,0],[0,0],[0,0],[0,0],[0,0],[0,0],[0,0],[0,0],[0,0],[0,0],[0,0],[0,0],[0,0],[0,0],[0,0],[0,0],[0,0],[0,0],[0,0],[0,0],[0,0],[0,0],[0,0],[0,0],[0,0],[0,0],[0,0],[0,0],[0,0],[0,0],[0,0],[0,0],[0,0],[0,0],[0,0],[0,0],[0,0],[0,0],[0,0],[0,0],[0,0],[0,0],[0,0],[0,0],[0,0],[0,0],[0,0],[0,0],[0,0],[0,0],[0,0],[0,0],[0,0],[0,0],[0,0],[0,0],[0,0],[0,0],[0,0],[0,0],[0,0],[0,0],[0,0],[0,0],[0,0],[0,0],[0,0],[0,0],[0,0],[0,0],[0,0],[0,0],[0,0],[0,0],[0,0],[0,0],[0,0],[0,0],[0,0],[0,0],[0,0],[0,0],[0,0],[0,0],[0,0],[0,0],[0,0],[0,0],[0,0],[0,0],[0,0],[0,0],[0,0],[0,0],[0,0],[0,0],[0,0],[0,0],[0,0],[0,0],[0,0],[0,0],[0,0],[0,0],[0,0],[0,0],[0,0],[0,0],[0,0],[0,0],[0,0],[0,0],[0,0],[0,0],[0,0],[0,0],[0,0],[0,0],[0,0],[0,0],[0,0],[0,0],[0,0],[0,0],[0,0],[0,0],[0,0],[0,0],[0,0],[0,0],[0,0],[0,0],[0,0],[0,0],[0,0],[0,0],[0,0],[0,0],[0,0],[0,0],[0,0],[0,0],[0,0],[0,0],[0,0],[0,0],[0,0],[0,0],[0,0],[0,0],[0,0],[0,0],[0,0],[0,0],[0,0],[0,0],[0,0],[0,0],[0,0],[0,0],[0,0],[0,0],[0,0],[0,0],[0,0],[0,0],[0,0],[0,0],[0,0],[0,0],[0,0],[0,0],[0,0],[0,0],[0,0],[0,0],[0,0],[0,0],[0,0],[0,0],[0,0],[0,0],[0,0],[0,0],[0,0],[0,0],[0,0],[0,0],[0,0],[0,0],[0,0],[0,0],[0,0],[0,0],[0,0],[0,0],[0,0],[0,0],[0,0],[0,0],[0,0],[0,0],[0,0],[0,0],[0,0],[0,0],[0,0],[0,0],[0,0],[0,0],[0,0],[0,0],[0,0],[0,0],[0,0],[0,0],[0,0],[0,0],[0,0],[0,0],[0,0],[0,0],[0,0],[0,0],[0,0],[0,0],[0,0],[0,0],[0,0],[0,0],[0,0],[0,0],[0,0],[0,0],[0,0],[0,0],[0,0],[0,0],[0,0],[0,0],[0,0],[0,0],[0,0],[0,0],[0,0],[0,0],[0,0],[0,0],[0,0],[0,0],[0,0],[0,0],[0,0],[0,0],[0,0],[0,0],[0,0],[0,0],[0,0],[0,0],[0,0],[0,0],[0,0],[0,0],[0,0],[0,0],[0,0],[0,0],[0,0],[0,0],[0,0],[0,0],[0,0],[0,0],[0,0],[0,0],[0,0],[0,0],[0,0],[0,0],[0,0],[0,0],[0,0],[0,0],[0,0],[0,0],[0,0],[0,0],[0,0],[0,0],[0,0],[0,0],[0,0],[0,0],[0,0],[0,0],[0,0],[0,0],[0,0],[0,0],[0,0],[0,0],[0,0],[0,0],[0,0],[0,0],[0,0],[0,0],[0,0],[0,0],[0,0],[0,0],[0,0],[0,0],[0,0],[0,0],[0,0],[0,0],[0,0],[0,0],[0,0],[0,0],[0,0],[0,0],[0,0],[0,0],[0,0],[0,0],[0,0],[0,0],[0,0],[0,0],[0,0],[0,0],[0,0],[0,0],[0,0],[0,0],[0,0],[0,0],[0,0],[0,0],[0,0],[0,0],[0,0],[0,0],[0,0],[0,0],[0,0],[0,0],[0,0],[0,0],[0,0],[0,0],[0,0],[0,0],[0,0],[0,0],[0,0],[0,0],[0,0],[0,0],[0,0],[0,0],[0,0],[0,0],[0,0],[0,0],[0,0],[0,0],[0,0],[0,0],[0,0],[0,0],[0,0],[0,0],[0,0],[0,0],[0,0],[0,0],[0,0],[0,0],[0,0],[0,0],[0,0],[0,0],[0,0],[0,0],[0,0],[0,0],[0,0],[0,0],[0,0],[0,0],[0,0],[0,0],[0,0],[0,0],[0,0],[0,0],[0,0],[0,0],[0,0],[0,0],[0,0],[0,0],[0,0],[0,0],[0,0],[0,0],[0,0],[0,0],[0,0],[0,0],[0,0],[0,0],[0,0],[0,0],[0,0],[0,0],[0,0],[0,0],[0,0],[0,0],[0,0],[0,0],[0,0],[0,0],[0,0],[0,0],[0,0],[0,0],[0,0],[0,0],[0,0],[0,0],[0,0],[0,0],[0,0],[0,0],[0,0],[0,0],[0,0],[0,0],[0,0],[0,0],[0,0],[0,0],[0,0],[0,0],[0,0],[0,0],[0,0],[0,0],[0,0],[0,0],[0,0],[0,0],[0,0],[0,0],[0,0],[0,0],[0,0],[0,0],[0,0],[0,0],[0,0],[0,0],[0,0],[0,0],[0,0],[0,0],[0,0],[0,0],[0,0],[0,0],[0,0],[0,0],[0,0],[0,0],[0,0],[0,0],[0,0],[0,0],[0,0],[0,0],[0,0],[0,0],[0,0],[0,0],[0,0],[0,0],[0,0],[0,0],[0,0],[0,0],[0,0],[0,0],[0,0],[0,0],[0,0],[0,0],[0,0],[0,0],[0,0],[0,0],[0,0],[0,0],[0,0],[0,0],[0,0],[0,0],[0,0],[0,0],[0,0],[0,0],[0,0],[0,0],[0,0],[0,0],[0,0],[0,0],[0,0],[0,0],[0,0],[0,0],[0,0],[0,0],[0,0],[0,0],[0,0],[0,0],[0,0],[0,0],[0,0],[0,0],[0,0],[0,0],[0,0],[0,0],[0,0],[0,0],[0,0],[0,0],[0,0],[0,0],[0,0],[0,0],[0,0],[0,0],[0,0],[0,0],[0,0],[0,0],[0,0],[0,0],[0,0],[0,0],[0,0],[0,0],[0,0],[0,0],[0,0],[0,0],[0,0],[0,0],[0,0],[0,0],[0,0],[0,0],[0,0],[0,0],[0,0],[0,0],[0,0],[0,0],[0,0],[0,0],[0,0],[0,0],[0,0]],"o":[[0,0],[0,0],[0,0],[0,0],[0,0],[0,0],[0,0],[0,0],[0,0],[0,0],[0,0],[0,0],[0,0],[0,0],[0,0],[0,0],[0,0],[0,0],[0,0],[0,0],[0,0],[0,0],[0,0],[0,0],[0,0],[0,0],[0,0],[0,0],[0,0],[0,0],[0,0],[0,0],[0,0],[0,0],[0,0],[0,0],[0,0],[0,0],[0,0],[0,0],[0,0],[0,0],[0,0],[0,0],[0,0],[0,0],[0,0],[0,0],[0,0],[0,0],[0,0],[0,0],[0,0],[0,0],[0,0],[0,0],[0,0],[0,0],[0,0],[0,0],[0,0],[0,0],[0,0],[0,0],[0,0],[0,0],[0,0],[0,0],[0,0],[0,0],[0,0],[0,0],[0,0],[0,0],[0,0],[0,0],[0,0],[0,0],[0,0],[0,0],[0,0],[0,0],[0,0],[0,0],[0,0],[0,0],[0,0],[0,0],[0,0],[0,0],[0,0],[0,0],[0,0],[0,0],[0,0],[0,0],[0,0],[0,0],[0,0],[0,0],[0,0],[0,0],[0,0],[0,0],[0,0],[0,0],[0,0],[0,0],[0,0],[0,0],[0,0],[0,0],[0,0],[0,0],[0,0],[0,0],[0,0],[0,0],[0,0],[0,0],[0,0],[0,0],[0,0],[0,0],[0,0],[0,0],[0,0],[0,0],[0,0],[0,0],[0,0],[0,0],[0,0],[0,0],[0,0],[0,0],[0,0],[0,0],[0,0],[0,0],[0,0],[0,0],[0,0],[0,0],[0,0],[0,0],[0,0],[0,0],[0,0],[0,0],[0,0],[0,0],[0,0],[0,0],[0,0],[0,0],[0,0],[0,0],[0,0],[0,0],[0,0],[0,0],[0,0],[0,0],[0,0],[0,0],[0,0],[0,0],[0,0],[0,0],[0,0],[0,0],[0,0],[0,0],[0,0],[0,0],[0,0],[0,0],[0,0],[0,0],[0,0],[0,0],[0,0],[0,0],[0,0],[0,0],[0,0],[0,0],[0,0],[0,0],[0,0],[0,0],[0,0],[0,0],[0,0],[0,0],[0,0],[0,0],[0,0],[0,0],[0,0],[0,0],[0,0],[0,0],[0,0],[0,0],[0,0],[0,0],[0,0],[0,0],[0,0],[0,0],[0,0],[0,0],[0,0],[0,0],[0,0],[0,0],[0,0],[0,0],[0,0],[0,0],[0,0],[0,0],[0,0],[0,0],[0,0],[0,0],[0,0],[0,0],[0,0],[0,0],[0,0],[0,0],[0,0],[0,0],[0,0],[0,0],[0,0],[0,0],[0,0],[0,0],[0,0],[0,0],[0,0],[0,0],[0,0],[0,0],[0,0],[0,0],[0,0],[0,0],[0,0],[0,0],[0,0],[0,0],[0,0],[0,0],[0,0],[0,0],[0,0],[0,0],[0,0],[0,0],[0,0],[0,0],[0,0],[0,0],[0,0],[0,0],[0,0],[0,0],[0,0],[0,0],[0,0],[0,0],[0,0],[0,0],[0,0],[0,0],[0,0],[0,0],[0,0],[0,0],[0,0],[0,0],[0,0],[0,0],[0,0],[0,0],[0,0],[0,0],[0,0],[0,0],[0,0],[0,0],[0,0],[0,0],[0,0],[0,0],[0,0],[0,0],[0,0],[0,0],[0,0],[0,0],[0,0],[0,0],[0,0],[0,0],[0,0],[0,0],[0,0],[0,0],[0,0],[0,0],[0,0],[0,0],[0,0],[0,0],[0,0],[0,0],[0,0],[0,0],[0,0],[0,0],[0,0],[0,0],[0,0],[0,0],[0,0],[0,0],[0,0],[0,0],[0,0],[0,0],[0,0],[0,0],[0,0],[0,0],[0,0],[0,0],[0,0],[0,0],[0,0],[0,0],[0,0],[0,0],[0,0],[0,0],[0,0],[0,0],[0,0],[0,0],[0,0],[0,0],[0,0],[0,0],[0,0],[0,0],[0,0],[0,0],[0,0],[0,0],[0,0],[0,0],[0,0],[0,0],[0,0],[0,0],[0,0],[0,0],[0,0],[0,0],[0,0],[0,0],[0,0],[0,0],[0,0],[0,0],[0,0],[0,0],[0,0],[0,0],[0,0],[0,0],[0,0],[0,0],[0,0],[0,0],[0,0],[0,0],[0,0],[0,0],[0,0],[0,0],[0,0],[0,0],[0,0],[0,0],[0,0],[0,0],[0,0],[0,0],[0,0],[0,0],[0,0],[0,0],[0,0],[0,0],[0,0],[0,0],[0,0],[0,0],[0,0],[0,0],[0,0],[0,0],[0,0],[0,0],[0,0],[0,0],[0,0],[0,0],[0,0],[0,0],[0,0],[0,0],[0,0],[0,0],[0,0],[0,0],[0,0],[0,0],[0,0],[0,0],[0,0],[0,0],[0,0],[0,0],[0,0],[0,0],[0,0],[0,0],[0,0],[0,0],[0,0],[0,0],[0,0],[0,0],[0,0],[0,0],[0,0],[0,0],[0,0],[0,0],[0,0],[0,0],[0,0],[0,0],[0,0],[0,0],[0,0],[0,0],[0,0],[0,0],[0,0],[0,0],[0,0],[0,0],[0,0],[0,0],[0,0],[0,0],[0,0],[0,0],[0,0],[0,0],[0,0],[0,0],[0,0],[0,0],[0,0],[0,0],[0,0],[0,0],[0,0],[0,0],[0,0],[0,0],[0,0],[0,0],[0,0],[0,0],[0,0],[0,0],[0,0],[0,0],[0,0],[0,0],[0,0],[0,0],[0,0],[0,0],[0,0],[0,0],[0,0],[0,0],[0,0],[0,0],[0,0],[0,0],[0,0],[0,0],[0,0],[0,0],[0,0],[0,0],[0,0],[0,0],[0,0],[0,0],[0,0],[0,0],[0,0],[0,0],[0,0],[0,0],[0,0],[0,0],[0,0],[0,0],[0,0],[0,0],[0,0],[0,0],[0,0],[0,0],[0,0],[0,0],[0,0],[0,0],[0,0],[0,0],[0,0],[0,0],[0,0],[0,0],[0,0],[0,0],[0,0],[0,0],[0,0],[0,0],[0,0],[0,0],[0,0],[0,0],[0,0],[0,0],[0,0],[0,0],[0,0],[0,0],[0,0],[0,0],[0,0],[0,0],[0,0],[0,0],[0,0],[0,0],[0,0],[0,0],[0,0],[0,0],[0,0],[0,0],[0,0],[0,0],[0,0],[0,0],[0,0],[0,0],[0,0],[0,0],[0,0],[0,0],[0,0],[0,0],[0,0],[0,0],[0,0],[0,0],[0,0],[0,0],[0,0],[0,0],[0,0],[0,0],[0,0],[0,0],[0,0],[0,0],[0,0],[0,0],[0,0],[0,0],[0,0],[0,0],[0,0],[0,0],[0,0],[0,0],[0,0],[0,0],[0,0],[0,0],[0,0],[0,0],[0,0],[0,0],[0,0],[0,0],[0,0],[0,0],[0,0],[0,0],[0,0],[0,0],[0,0],[0,0],[0,0],[0,0],[0,0],[0,0],[0,0],[0,0],[0,0],[0,0],[0,0],[0,0],[0,0],[0,0],[0,0],[0,0],[0,0],[0,0],[0,0],[0,0],[0,0],[0,0],[0,0],[0,0],[0,0],[0,0],[0,0],[0,0],[0,0],[0,0],[0,0],[0,0],[0,0],[0,0],[0,0],[0,0],[0,0],[0,0],[0,0],[0,0],[0,0],[0,0],[0,0],[0,0],[0,0],[0,0],[0,0],[0,0],[0,0],[0,0],[0,0],[0,0],[0,0],[0,0],[0,0],[0,0],[0,0],[0,0],[0,0],[0,0],[0,0],[0,0],[0,0],[0,0],[0,0],[0,0],[0,0],[0,0],[0,0],[0,0],[0,0],[0,0],[0,0],[0,0],[0,0],[0,0],[0,0],[0,0],[0,0],[0,0],[0,0],[0,0],[0,0],[0,0],[0,0],[0,0],[0,0],[0,0],[0,0],[0,0],[0,0],[0,0],[0,0],[0,0],[0,0],[0,0],[0,0],[0,0],[0,0],[0,0],[0,0],[0,0],[0,0],[0,0],[0,0],[0,0],[0,0],[0,0],[0,0],[0,0],[0,0],[0,0],[0,0],[0,0],[0,0],[0,0],[0,0],[0,0],[0,0],[0,0],[0,0],[0,0],[0,0],[0,0],[0,0],[0,0],[0,0],[0,0],[0,0],[0,0],[0,0],[0,0],[0,0],[0,0],[0,0],[0,0],[0,0],[0,0],[0,0],[0,0],[0,0],[0,0],[0,0],[0,0],[0,0],[0,0],[0,0],[0,0],[0,0],[0,0],[0,0],[0,0],[0,0],[0,0],[0,0],[0,0],[0,0],[0,0],[0,0],[0,0],[0,0],[0,0],[0,0],[0,0],[0,0],[0,0],[0,0],[0,0],[0,0],[0,0],[0,0],[0,0],[0,0],[0,0],[0,0],[0,0],[0,0],[0,0],[0,0],[0,0],[0,0],[0,0],[0,0],[0,0],[0,0],[0,0],[0,0],[0,0],[0,0],[0,0],[0,0],[0,0],[0,0],[0,0],[0,0],[0,0],[0,0],[0,0],[0,0],[0,0],[0,0],[0,0],[0,0],[0,0],[0,0],[0,0],[0,0],[0,0],[0,0],[0,0],[0,0],[0,0],[0,0],[0,0],[0,0],[0,0],[0,0],[0,0],[0,0],[0,0],[0,0],[0,0],[0,0],[0,0],[0,0],[0,0],[0,0],[0,0],[0,0],[0,0],[0,0],[0,0],[0,0],[0,0],[0,0],[0,0],[0,0],[0,0],[0,0],[0,0],[0,0],[0,0],[0,0],[0,0],[0,0],[0,0],[0,0],[0,0],[0,0],[0,0],[0,0],[0,0],[0,0],[0,0],[0,0],[0,0],[0,0],[0,0],[0,0],[0,0],[0,0],[0,0],[0,0],[0,0],[0,0],[0,0],[0,0],[0,0],[0,0],[0,0],[0,0],[0,0],[0,0],[0,0],[0,0],[0,0],[0,0],[0,0],[0,0],[0,0],[0,0],[0,0],[0,0],[0,0],[0,0],[0,0],[0,0],[0,0],[0,0],[0,0],[0,0],[0,0],[0,0],[0,0],[0,0],[0,0],[0,0],[0,0],[0,0],[0,0],[0,0],[0,0],[0,0],[0,0],[0,0],[0,0],[0,0],[0,0],[0,0],[0,0],[0,0],[0,0],[0,0],[0,0],[0,0],[0,0],[0,0],[0,0],[0,0],[0,0],[0,0],[0,0],[0,0],[0,0],[0,0],[0,0],[0,0],[0,0],[0,0],[0,0],[0,0],[0,0],[0,0],[0,0],[0,0],[0,0],[0,0],[0,0],[0,0],[0,0],[0,0],[0,0],[0,0],[0,0],[0,0],[0,0],[0,0],[0,0],[0,0],[0,0],[0,0],[0,0],[0,0],[0,0],[0,0],[0,0],[0,0],[0,0],[0,0],[0,0],[0,0],[0,0],[0,0],[0,0],[0,0],[0,0],[0,0],[0,0],[0,0],[0,0],[0,0],[0,0],[0,0],[0,0],[0,0],[0,0],[0,0],[0,0],[0,0],[0,0],[0,0],[0,0],[0,0],[0,0],[0,0],[0,0],[0,0],[0,0],[0,0],[0,0],[0,0],[0,0],[0,0],[0,0],[0,0],[0,0],[0,0],[0,0],[0,0],[0,0],[0,0],[0,0],[0,0],[0,0],[0,0],[0,0],[0,0],[0,0],[0,0],[0,0],[0,0],[0,0],[0,0],[0,0],[0,0],[0,0],[0,0],[0,0],[0,0],[0,0],[0,0],[0,0],[0,0],[0,0],[0,0],[0,0],[0,0],[0,0],[0,0],[0,0],[0,0],[0,0],[0,0],[0,0],[0,0],[0,0],[0,0],[0,0],[0,0],[0,0],[0,0],[0,0],[0,0],[0,0],[0,0],[0,0],[0,0],[0,0],[0,0],[0,0],[0,0],[0,0],[0,0],[0,0],[0,0],[0,0],[0,0],[0,0],[0,0],[0,0],[0,0],[0,0],[0,0],[0,0],[0,0],[0,0],[0,0],[0,0],[0,0],[0,0],[0,0],[0,0],[0,0],[0,0],[0,0],[0,0],[0,0],[0,0],[0,0],[0,0],[0,0],[0,0],[0,0],[0,0],[0,0],[0,0],[0,0],[0,0],[0,0],[0,0],[0,0],[0,0],[0,0],[0,0],[0,0],[0,0],[0,0],[0,0],[0,0],[0,0],[0,0],[0,0],[0,0],[0,0],[0,0],[0,0],[0,0],[0,0],[0,0],[0,0],[0,0],[0,0],[0,0],[0,0],[0,0],[0,0],[0,0],[0,0],[0,0],[0,0],[0,0],[0,0]],"v":[[-51.706,-65.099],[-51.766,-65.099],[-51.825,-65.099],[-51.884,-65.099],[-51.942,-65.098],[-52.001,-65.097],[-52.059,-65.096],[-52.119,-65.095],[-52.177,-65.093],[-52.236,-65.092],[-52.295,-65.09],[-52.352,-65.088],[-52.411,-65.086],[-52.47,-65.084],[-52.527,-65.081],[-52.585,-65.079],[-52.645,-65.076],[-52.702,-65.073],[-52.761,-65.069],[-52.818,-65.066],[-52.877,-65.062],[-52.935,-65.059],[-52.993,-65.055],[-53.05,-65.051],[-53.109,-65.046],[-53.167,-65.042],[-53.223,-65.037],[-53.282,-65.032],[-53.34,-65.027],[-53.396,-65.022],[-53.455,-65.017],[-53.512,-65.011],[-53.57,-65.005],[-53.627,-64.999],[-53.685,-64.993],[-53.742,-64.987],[-53.799,-64.98],[-53.856,-64.974],[-53.912,-64.967],[-53.97,-64.96],[-54.027,-64.953],[-54.084,-64.946],[-54.141,-64.938],[-54.197,-64.93],[-54.255,-64.922],[-54.312,-64.914],[-54.368,-64.906],[-54.424,-64.898],[-54.482,-64.889],[-54.537,-64.881],[-54.594,-64.872],[-54.706,-64.853],[-54.82,-64.834],[-54.932,-64.815],[-55.044,-64.794],[-55.156,-64.773],[-55.268,-64.751],[-55.379,-64.729],[-55.489,-64.706],[-55.601,-64.682],[-55.711,-64.657],[-55.822,-64.632],[-55.932,-64.607],[-56.042,-64.58],[-56.151,-64.553],[-56.26,-64.525],[-56.369,-64.497],[-56.477,-64.468],[-56.587,-64.438],[-56.695,-64.407],[-56.803,-64.376],[-56.911,-64.345],[-57.018,-64.312],[-57.124,-64.279],[-57.232,-64.246],[-57.339,-64.211],[-57.445,-64.177],[-57.55,-64.141],[-57.657,-64.105],[-57.761,-64.068],[-57.867,-64.031],[-57.972,-63.993],[-58.076,-63.954],[-58.18,-63.915],[-58.285,-63.875],[-58.388,-63.834],[-58.491,-63.793],[-58.593,-63.751],[-58.697,-63.709],[-58.8,-63.666],[-58.902,-63.623],[-59.003,-63.578],[-59.105,-63.534],[-59.206,-63.488],[-59.307,-63.442],[-59.407,-63.396],[-59.507,-63.349],[-59.606,-63.301],[-59.706,-63.253],[-59.805,-63.204],[-59.904,-63.154],[-60.003,-63.104],[-60.101,-63.053],[-60.197,-63.002],[-60.295,-62.95],[-60.393,-62.898],[-60.489,-62.845],[-60.586,-62.792],[-60.682,-62.738],[-60.777,-62.683],[-60.873,-62.628],[-60.967,-62.572],[-61.062,-62.516],[-61.156,-62.459],[-61.249,-62.402],[-61.343,-62.344],[-61.436,-62.285],[-61.529,-62.226],[-61.622,-62.167],[-61.713,-62.106],[-61.806,-62.046],[-61.896,-61.985],[-61.986,-61.923],[-62.077,-61.861],[-62.167,-61.798],[-62.256,-61.735],[-62.344,-61.671],[-62.433,-61.606],[-62.521,-61.542],[-62.61,-61.476],[-62.697,-61.41],[-62.785,-61.344],[-62.872,-61.277],[-62.958,-61.21],[-63.044,-61.142],[-63.128,-61.073],[-63.213,-61.004],[-63.299,-60.935],[-63.383,-60.865],[-63.467,-60.795],[-63.55,-60.724],[-63.632,-60.652],[-63.715,-60.58],[-63.798,-60.508],[-63.879,-60.435],[-63.961,-60.362],[-64.04,-60.288],[-64.122,-60.214],[-64.201,-60.139],[-64.281,-60.064],[-64.36,-59.988],[-64.437,-59.912],[-64.516,-59.835],[-64.593,-59.758],[-64.671,-59.681],[-64.747,-59.603],[-64.824,-59.524],[-64.899,-59.445],[-64.975,-59.366],[-65.049,-59.286],[-65.124,-59.206],[-65.197,-59.125],[-65.271,-59.044],[-65.343,-58.962],[-65.416,-58.88],[-65.488,-58.798],[-65.559,-58.715],[-65.63,-58.631],[-65.701,-58.548],[-65.77,-58.463],[-65.839,-58.379],[-65.909,-58.294],[-65.977,-58.208],[-66.045,-58.122],[-66.113,-58.036],[-66.18,-57.949],[-66.245,-57.862],[-66.312,-57.774],[-66.377,-57.686],[-66.442,-57.598],[-66.506,-57.509],[-66.57,-57.421],[-66.633,-57.33],[-66.695,-57.241],[-66.758,-57.151],[-66.82,-57.06],[-66.881,-56.968],[-66.942,-56.877],[-67.002,-56.785],[-67.062,-56.693],[-67.12,-56.601],[-67.179,-56.507],[-67.237,-56.414],[-67.295,-56.32],[-67.351,-56.226],[-67.407,-56.132],[-67.463,-56.037],[-67.519,-55.942],[-67.572,-55.846],[-67.627,-55.75],[-67.681,-55.654],[-67.734,-55.557],[-67.786,-55.46],[-67.838,-55.363],[-67.889,-55.265],[-67.939,-55.167],[-67.99,-55.069],[-68.039,-54.97],[-68.088,-54.871],[-68.136,-54.771],[-68.184,-54.671],[-68.231,-54.571],[-68.277,-54.471],[-68.324,-54.37],[-68.369,-54.269],[-68.414,-54.168],[-68.458,-54.066],[-68.502,-53.964],[-68.545,-53.862],[-68.587,-53.759],[-68.628,-53.656],[-68.67,-53.553],[-68.71,-53.449],[-68.749,-53.345],[-68.79,-53.241],[-68.827,-53.136],[-68.866,-53.031],[-68.904,-52.926],[-68.94,-52.821],[-68.977,-52.715],[-69.011,-52.609],[-69.046,-52.503],[-69.08,-52.396],[-69.115,-52.29],[-69.148,-52.182],[-69.18,-52.075],[-69.212,-51.967],[-69.243,-51.859],[-69.273,-51.751],[-69.303,-51.643],[-69.331,-51.534],[-69.361,-51.425],[-69.389,-51.316],[-69.416,-51.206],[-69.442,-51.096],[-69.468,-50.986],[-69.493,-50.876],[-69.518,-50.765],[-69.541,-50.654],[-69.564,-50.543],[-69.587,-50.432],[-69.609,-50.32],[-69.63,-50.209],[-69.649,-50.097],[-69.67,-49.984],[-69.689,-49.872],[-69.706,-49.759],[-69.715,-49.703],[-69.725,-49.646],[-69.732,-49.589],[-69.742,-49.533],[-69.75,-49.476],[-69.758,-49.419],[-69.766,-49.363],[-69.774,-49.306],[-69.781,-49.249],[-69.788,-49.192],[-69.796,-49.135],[-69.803,-49.078],[-69.809,-49.021],[-69.816,-48.964],[-69.822,-48.906],[-69.829,-48.849],[-69.835,-48.792],[-69.84,-48.734],[-69.847,-48.677],[-69.851,-48.619],[-69.859,-48.562],[-69.864,-48.504],[-69.868,-48.447],[-69.873,-48.389],[-69.878,-48.331],[-69.881,-48.273],[-69.886,-48.215],[-69.89,-48.158],[-69.894,-48.1],[-69.899,-48.042],[-69.902,-47.984],[-69.906,-47.925],[-69.908,-47.867],[-69.911,-47.809],[-69.914,-47.751],[-69.917,-47.693],[-69.919,-47.634],[-69.923,-47.576],[-69.925,-47.517],[-69.925,-47.459],[-69.926,-47.4],[-69.93,-47.342],[-69.93,-47.283],[-69.932,-47.225],[-69.933,-47.166],[-69.933,-47.107],[-69.933,-47.048],[-69.934,-46.989],[-69.934,-46.931],[-69.934,-46.872],[-69.934,46.871],[-69.934,46.93],[-69.934,46.989],[-69.933,47.048],[-69.933,47.106],[-69.933,47.165],[-69.932,47.224],[-69.93,47.283],[-69.93,47.341],[-69.926,47.4],[-69.925,47.458],[-69.925,47.517],[-69.923,47.575],[-69.919,47.634],[-69.917,47.692],[-69.914,47.75],[-69.911,47.808],[-69.908,47.867],[-69.906,47.925],[-69.902,47.983],[-69.899,48.041],[-69.894,48.099],[-69.89,48.157],[-69.886,48.215],[-69.881,48.273],[-69.878,48.33],[-69.873,48.388],[-69.868,48.446],[-69.864,48.503],[-69.859,48.561],[-69.851,48.619],[-69.847,48.676],[-69.84,48.734],[-69.835,48.791],[-69.829,48.848],[-69.822,48.906],[-69.816,48.963],[-69.809,49.02],[-69.803,49.077],[-69.796,49.134],[-69.788,49.191],[-69.781,49.248],[-69.774,49.305],[-69.766,49.362],[-69.758,49.419],[-69.75,49.475],[-69.742,49.532],[-69.732,49.589],[-69.725,49.645],[-69.715,49.702],[-69.706,49.758],[-69.689,49.871],[-69.67,49.984],[-69.649,50.096],[-69.63,50.208],[-69.609,50.32],[-69.587,50.431],[-69.564,50.543],[-69.541,50.654],[-69.518,50.765],[-69.493,50.875],[-69.468,50.985],[-69.442,51.095],[-69.416,51.205],[-69.389,51.315],[-69.361,51.424],[-69.331,51.533],[-69.303,51.642],[-69.273,51.75],[-69.243,51.859],[-69.212,51.967],[-69.18,52.074],[-69.148,52.182],[-69.115,52.289],[-69.08,52.396],[-69.046,52.502],[-69.011,52.609],[-68.977,52.715],[-68.94,52.82],[-68.904,52.926],[-68.866,53.031],[-68.827,53.136],[-68.79,53.24],[-68.749,53.344],[-68.71,53.448],[-68.67,53.552],[-68.628,53.655],[-68.587,53.758],[-68.545,53.861],[-68.502,53.963],[-68.458,54.065],[-68.414,54.167],[-68.369,54.268],[-68.324,54.369],[-68.277,54.47],[-68.231,54.571],[-68.184,54.671],[-68.136,54.771],[-68.088,54.87],[-68.039,54.969],[-67.99,55.068],[-67.939,55.166],[-67.889,55.264],[-67.838,55.362],[-67.786,55.459],[-67.734,55.556],[-67.681,55.653],[-67.627,55.749],[-67.572,55.845],[-67.519,55.941],[-67.463,56.036],[-67.407,56.131],[-67.351,56.226],[-67.295,56.32],[-67.237,56.414],[-67.179,56.507],[-67.12,56.6],[-67.062,56.693],[-67.002,56.786],[-66.942,56.877],[-66.881,56.968],[-66.82,57.059],[-66.758,57.15],[-66.695,57.24],[-66.633,57.33],[-66.57,57.42],[-66.506,57.509],[-66.442,57.598],[-66.377,57.686],[-66.312,57.774],[-66.245,57.862],[-66.18,57.949],[-66.113,58.035],[-66.045,58.122],[-65.977,58.208],[-65.909,58.293],[-65.839,58.378],[-65.77,58.463],[-65.701,58.547],[-65.63,58.631],[-65.559,58.714],[-65.488,58.797],[-65.416,58.879],[-65.343,58.961],[-65.271,59.043],[-65.197,59.124],[-65.124,59.205],[-65.049,59.285],[-64.975,59.365],[-64.899,59.444],[-64.824,59.523],[-64.747,59.602],[-64.671,59.68],[-64.593,59.757],[-64.516,59.835],[-64.437,59.911],[-64.36,59.987],[-64.281,60.063],[-64.201,60.138],[-64.122,60.213],[-64.04,60.287],[-63.961,60.361],[-63.879,60.434],[-63.798,60.507],[-63.715,60.58],[-63.632,60.652],[-63.55,60.723],[-63.467,60.794],[-63.383,60.864],[-63.299,60.934],[-63.213,61.004],[-63.128,61.073],[-63.044,61.141],[-62.958,61.209],[-62.872,61.276],[-62.785,61.343],[-62.697,61.41],[-62.61,61.476],[-62.521,61.541],[-62.433,61.606],[-62.344,61.67],[-62.256,61.734],[-62.167,61.797],[-62.077,61.86],[-61.986,61.922],[-61.896,61.984],[-61.806,62.045],[-61.713,62.106],[-61.622,62.166],[-61.529,62.225],[-61.436,62.284],[-61.343,62.343],[-61.249,62.401],[-61.156,62.458],[-61.062,62.515],[-60.967,62.571],[-60.873,62.627],[-60.777,62.682],[-60.682,62.737],[-60.586,62.791],[-60.489,62.844],[-60.393,62.897],[-60.295,62.95],[-60.197,63.002],[-60.101,63.053],[-60.003,63.103],[-59.904,63.153],[-59.805,63.203],[-59.706,63.252],[-59.606,63.3],[-59.507,63.348],[-59.407,63.395],[-59.307,63.442],[-59.206,63.488],[-59.105,63.533],[-59.003,63.578],[-58.902,63.622],[-58.8,63.665],[-58.697,63.708],[-58.593,63.751],[-58.491,63.792],[-58.388,63.834],[-58.285,63.874],[-58.18,63.914],[-58.076,63.953],[-57.972,63.992],[-57.867,64.03],[-57.761,64.067],[-57.657,64.104],[-57.55,64.14],[-57.445,64.176],[-57.339,64.211],[-57.232,64.245],[-57.124,64.279],[-57.018,64.312],[-56.911,64.344],[-56.803,64.376],[-56.695,64.407],[-56.587,64.437],[-56.477,64.467],[-56.369,64.496],[-56.26,64.524],[-56.151,64.552],[-56.042,64.579],[-55.932,64.606],[-55.822,64.632],[-55.711,64.657],[-55.601,64.681],[-55.489,64.705],[-55.379,64.728],[-55.268,64.751],[-55.156,64.772],[-55.044,64.793],[-54.932,64.814],[-54.82,64.834],[-54.706,64.853],[-54.594,64.871],[-54.537,64.88],[-54.482,64.889],[-54.424,64.897],[-54.368,64.906],[-54.312,64.914],[-54.255,64.922],[-54.197,64.931],[-54.141,64.938],[-54.084,64.945],[-54.027,64.952],[-53.97,64.959],[-53.912,64.966],[-53.856,64.973],[-53.799,64.98],[-53.742,64.986],[-53.685,64.993],[-53.627,64.999],[-53.57,65.005],[-53.512,65.011],[-53.455,65.016],[-53.396,65.021],[-53.34,65.028],[-53.282,65.032],[-53.223,65.037],[-53.167,65.042],[-53.109,65.046],[-53.05,65.05],[-52.993,65.054],[-52.935,65.058],[-52.877,65.063],[-52.818,65.065],[-52.761,65.07],[-52.702,65.072],[-52.645,65.075],[-52.585,65.078],[-52.527,65.082],[-52.47,65.083],[-52.411,65.085],[-52.352,65.089],[-52.295,65.089],[-52.236,65.091],[-52.177,65.094],[-52.119,65.094],[-52.059,65.096],[-52.001,65.096],[-51.942,65.097],[-51.884,65.098],[-51.825,65.098],[-51.766,65.099],[51.765,65.099],[51.824,65.098],[51.883,65.098],[52.059,65.096],[52.117,65.094],[52.176,65.094],[52.293,65.089],[52.352,65.089],[52.41,65.085],[52.527,65.082],[52.586,65.078],[52.644,65.075],[52.76,65.07],[52.819,65.065],[52.876,65.063],[53.109,65.046],[53.165,65.042],[53.281,65.032],[53.339,65.028],[53.396,65.021],[53.454,65.016],[53.511,65.011],[53.569,65.005],[53.684,64.993],[53.741,64.986],[53.799,64.98],[54.197,64.931],[54.311,64.914],[54.367,64.906],[54.424,64.897],[54.48,64.889],[54.538,64.88],[54.593,64.871],[54.706,64.853],[54.82,64.834],[54.931,64.814],[55.155,64.772],[55.266,64.751],[55.378,64.728],[55.489,64.705],[55.6,64.681],[55.711,64.657],[55.822,64.632],[55.931,64.606],[56.04,64.579],[56.15,64.552],[56.368,64.496],[56.477,64.467],[56.587,64.437],[56.695,64.407],[56.802,64.376],[56.91,64.344],[57.018,64.312],[57.124,64.279],[57.231,64.245],[57.337,64.211],[57.445,64.176],[57.55,64.14],[57.656,64.104],[57.761,64.067],[57.866,64.03],[57.972,63.992],[58.18,63.914],[58.388,63.834],[58.49,63.792],[58.593,63.751],[58.696,63.708],[58.9,63.622],[59.002,63.578],[59.104,63.533],[59.205,63.488],[59.305,63.442],[59.406,63.395],[59.506,63.348],[59.606,63.3],[59.706,63.252],[59.804,63.203],[59.903,63.153],[60.099,63.053],[60.197,63.002],[60.296,62.95],[60.393,62.897],[60.488,62.844],[60.586,62.791],[60.68,62.737],[60.776,62.682],[60.872,62.627],[61.061,62.515],[61.249,62.401],[61.342,62.343],[61.529,62.225],[61.62,62.166],[61.712,62.106],[61.894,61.984],[62.076,61.86],[62.165,61.797],[62.255,61.734],[62.433,61.606],[62.609,61.476],[62.697,61.41],[62.871,61.276],[62.957,61.209],[63.044,61.141],[63.129,61.073],[63.213,61.004],[63.298,60.934],[63.467,60.794],[63.632,60.652],[63.715,60.58],[63.797,60.507],[63.959,60.361],[64.04,60.287],[64.12,60.213],[64.28,60.063],[64.358,59.987],[64.437,59.911],[64.515,59.835],[64.67,59.68],[64.746,59.602],[64.898,59.444],[64.973,59.365],[65.049,59.285],[65.123,59.205],[65.27,59.043],[65.342,58.961],[65.415,58.879],[65.487,58.797],[65.629,58.631],[65.769,58.463],[65.84,58.378],[65.908,58.293],[65.977,58.208],[66.044,58.122],[66.111,58.035],[66.178,57.949],[66.245,57.862],[66.311,57.774],[66.441,57.598],[66.569,57.42],[66.695,57.24],[66.757,57.15],[66.82,57.059],[66.942,56.877],[67.061,56.693],[67.12,56.6],[67.236,56.414],[67.351,56.226],[67.407,56.131],[67.518,55.941],[67.572,55.845],[67.681,55.653],[67.733,55.556],[67.837,55.362],[67.889,55.264],[67.938,55.166],[67.989,55.068],[68.087,54.87],[68.135,54.771],[68.183,54.671],[68.23,54.571],[68.277,54.47],[68.323,54.369],[68.413,54.167],[68.457,54.065],[68.543,53.861],[68.587,53.758],[68.628,53.655],[68.669,53.552],[68.749,53.344],[68.827,53.136],[68.903,52.926],[68.939,52.82],[68.975,52.715],[69.011,52.609],[69.046,52.502],[69.081,52.396],[69.114,52.289],[69.148,52.182],[69.179,52.074],[69.211,51.967],[69.242,51.859],[69.272,51.75],[69.302,51.642],[69.36,51.424],[69.387,51.315],[69.441,51.095],[69.467,50.985],[69.493,50.875],[69.516,50.765],[69.541,50.654],[69.563,50.543],[69.586,50.431],[69.608,50.32],[69.63,50.208],[69.669,49.984],[69.688,49.871],[69.706,49.758],[69.715,49.702],[69.724,49.645],[69.732,49.589],[69.742,49.532],[69.749,49.475],[69.757,49.419],[69.765,49.362],[69.772,49.305],[69.78,49.248],[69.816,48.963],[69.821,48.906],[69.828,48.848],[69.84,48.734],[69.846,48.676],[69.851,48.619],[69.857,48.561],[69.862,48.503],[69.868,48.446],[69.872,48.388],[69.876,48.33],[69.881,48.273],[69.898,48.041],[69.9,47.983],[69.905,47.925],[69.916,47.692],[69.92,47.575],[69.924,47.517],[69.925,47.458],[69.926,47.4],[69.928,47.341],[69.931,47.224],[69.932,47.165],[69.932,47.106],[69.933,47.048],[69.933,46.989],[69.935,46.93],[69.935,-46.931],[69.933,-46.989],[69.933,-47.048],[69.932,-47.107],[69.932,-47.166],[69.931,-47.225],[69.929,-47.283],[69.928,-47.342],[69.926,-47.4],[69.925,-47.459],[69.924,-47.517],[69.92,-47.576],[69.918,-47.634],[69.916,-47.693],[69.913,-47.751],[69.91,-47.809],[69.907,-47.867],[69.905,-47.925],[69.9,-47.984],[69.898,-48.042],[69.894,-48.1],[69.89,-48.158],[69.885,-48.215],[69.881,-48.273],[69.876,-48.331],[69.872,-48.389],[69.868,-48.447],[69.862,-48.504],[69.857,-48.562],[69.851,-48.619],[69.846,-48.677],[69.84,-48.734],[69.834,-48.792],[69.828,-48.849],[69.821,-48.906],[69.816,-48.964],[69.808,-49.021],[69.801,-49.078],[69.794,-49.135],[69.787,-49.192],[69.78,-49.249],[69.772,-49.306],[69.765,-49.363],[69.757,-49.419],[69.749,-49.476],[69.742,-49.533],[69.732,-49.589],[69.724,-49.646],[69.715,-49.703],[69.706,-49.759],[69.688,-49.872],[69.669,-49.984],[69.649,-50.097],[69.63,-50.209],[69.608,-50.32],[69.586,-50.432],[69.563,-50.543],[69.541,-50.654],[69.516,-50.765],[69.493,-50.876],[69.467,-50.986],[69.441,-51.096],[69.415,-51.206],[69.387,-51.316],[69.36,-51.425],[69.331,-51.534],[69.302,-51.643],[69.272,-51.751],[69.242,-51.859],[69.211,-51.967],[69.179,-52.075],[69.148,-52.182],[69.114,-52.29],[69.081,-52.396],[69.046,-52.503],[69.011,-52.609],[68.975,-52.715],[68.939,-52.821],[68.903,-52.926],[68.865,-53.031],[68.827,-53.136],[68.788,-53.241],[68.749,-53.345],[68.709,-53.449],[68.669,-53.553],[68.628,-53.656],[68.587,-53.759],[68.543,-53.862],[68.5,-53.964],[68.457,-54.066],[68.413,-54.168],[68.368,-54.269],[68.323,-54.37],[68.277,-54.471],[68.23,-54.571],[68.183,-54.671],[68.135,-54.771],[68.087,-54.871],[68.038,-54.97],[67.989,-55.069],[67.938,-55.167],[67.889,-55.265],[67.837,-55.363],[67.785,-55.46],[67.733,-55.557],[67.681,-55.654],[67.626,-55.75],[67.572,-55.846],[67.518,-55.942],[67.462,-56.037],[67.407,-56.132],[67.351,-56.226],[67.293,-56.32],[67.236,-56.414],[67.178,-56.507],[67.12,-56.601],[67.061,-56.693],[67.002,-56.785],[66.942,-56.877],[66.88,-56.968],[66.82,-57.06],[66.757,-57.151],[66.695,-57.241],[66.632,-57.33],[66.569,-57.421],[66.505,-57.509],[66.441,-57.598],[66.376,-57.686],[66.311,-57.774],[66.245,-57.862],[66.178,-57.949],[66.111,-58.036],[66.044,-58.122],[65.977,-58.208],[65.908,-58.294],[65.84,-58.379],[65.769,-58.463],[65.699,-58.548],[65.629,-58.631],[65.558,-58.715],[65.487,-58.798],[65.415,-58.88],[65.342,-58.962],[65.27,-59.044],[65.197,-59.125],[65.123,-59.206],[65.049,-59.286],[64.973,-59.366],[64.898,-59.445],[64.822,-59.524],[64.746,-59.603],[64.67,-59.681],[64.593,-59.758],[64.515,-59.835],[64.437,-59.912],[64.358,-59.988],[64.28,-60.064],[64.2,-60.139],[64.12,-60.214],[64.04,-60.288],[63.959,-60.362],[63.879,-60.435],[63.797,-60.508],[63.715,-60.58],[63.632,-60.652],[63.549,-60.724],[63.467,-60.795],[63.382,-60.865],[63.298,-60.935],[63.213,-61.004],[63.129,-61.073],[63.044,-61.142],[62.957,-61.21],[62.871,-61.277],[62.784,-61.344],[62.697,-61.41],[62.609,-61.476],[62.521,-61.542],[62.433,-61.606],[62.344,-61.671],[62.255,-61.735],[62.165,-61.798],[62.076,-61.861],[61.986,-61.923],[61.894,-61.985],[61.804,-62.046],[61.712,-62.106],[61.62,-62.167],[61.529,-62.226],[61.436,-62.285],[61.342,-62.344],[61.249,-62.402],[61.155,-62.459],[61.061,-62.516],[60.966,-62.572],[60.872,-62.628],[60.776,-62.683],[60.68,-62.738],[60.586,-62.792],[60.488,-62.845],[60.393,-62.898],[60.296,-62.95],[60.197,-63.002],[60.099,-63.053],[60.001,-63.104],[59.903,-63.154],[59.804,-63.204],[59.706,-63.253],[59.606,-63.301],[59.506,-63.349],[59.406,-63.396],[59.305,-63.442],[59.205,-63.488],[59.104,-63.534],[59.002,-63.578],[58.9,-63.623],[58.798,-63.666],[58.696,-63.709],[58.593,-63.751],[58.49,-63.793],[58.388,-63.834],[58.284,-63.875],[58.18,-63.915],[58.076,-63.954],[57.972,-63.993],[57.866,-64.031],[57.761,-64.068],[57.656,-64.105],[57.55,-64.141],[57.445,-64.177],[57.337,-64.211],[57.231,-64.246],[57.124,-64.279],[57.018,-64.312],[56.91,-64.345],[56.802,-64.376],[56.695,-64.407],[56.587,-64.438],[56.477,-64.468],[56.368,-64.497],[56.259,-64.525],[56.15,-64.553],[56.04,-64.58],[55.931,-64.607],[55.822,-64.632],[55.711,-64.657],[55.6,-64.682],[55.489,-64.706],[55.378,-64.729],[55.266,-64.751],[55.155,-64.773],[55.043,-64.794],[54.931,-64.815],[54.82,-64.834],[54.706,-64.853],[54.593,-64.872],[54.538,-64.881],[54.48,-64.889],[54.424,-64.898],[54.367,-64.906],[54.311,-64.914],[54.254,-64.922],[54.197,-64.93],[54.14,-64.938],[54.083,-64.946],[54.026,-64.953],[53.97,-64.96],[53.912,-64.967],[53.855,-64.974],[53.799,-64.98],[53.741,-64.987],[53.684,-64.993],[53.626,-64.999],[53.569,-65.005],[53.511,-65.011],[53.454,-65.017],[53.396,-65.022],[53.339,-65.027],[53.281,-65.032],[53.223,-65.037],[53.165,-65.042],[53.109,-65.046],[53.05,-65.051],[52.993,-65.055],[52.934,-65.059],[52.876,-65.062],[52.819,-65.066],[52.76,-65.069],[52.701,-65.073],[52.644,-65.076],[52.586,-65.079],[52.527,-65.081],[52.47,-65.084],[52.41,-65.086],[52.352,-65.088],[52.293,-65.09],[52.236,-65.092],[52.176,-65.093],[52.117,-65.095],[52.059,-65.096],[52,-65.097],[51.942,-65.098],[51.883,-65.099],[51.824,-65.099],[51.765,-65.099],[51.706,-65.099]],"c":true},"ix":2},"nm":"Caminho 2","mn":"ADBE Vector Shape - Group","hd":false},{"ty":"mm","mm":1,"nm":"Mesclar caminhos 1","mn":"ADBE Vector Filter - Merge","hd":false},{"ty":"fl","c":{"a":0,"k":[1,1,1,1],"ix":4},"o":{"a":0,"k":100,"ix":5},"r":1,"bm":0,"nm":"Preenchimento 1","mn":"ADBE Vector Graphic - Fill","hd":false},{"ty":"tr","p":{"a":0,"k":[77.934,176.901],"ix":2},"a":{"a":0,"k":[0,0],"ix":1},"s":{"a":0,"k":[100,100],"ix":3},"r":{"a":0,"k":0,"ix":6},"o":{"a":0,"k":100,"ix":7},"sk":{"a":0,"k":0,"ix":4},"sa":{"a":0,"k":0,"ix":5},"nm":"Transformar"}],"nm":"Grupo 4","np":4,"cix":2,"bm":0,"ix":3,"mn":"ADBE Vector Group","hd":false}],"ip":0,"op":750,"st":0,"bm":0}],"markers":[]}